Workbook

Sheet PERSONAL BUDGET 2022-2023
A1: 2022 | B1: AUGUST | C1: SEPTEMBER | D1: OCTOBER | E1: NOVEMBER | F1: DECEMBER | G1: JANUARY | H1: FEBURARY | I1: MARCH | J1: APRIL | K1: MAY | L1: JUNE | M1: JULY | O1: TOTAL
A3: RENT | B3: 650 | O3: =SUM(B3:M3) -> 650
A4: STUDIO RENT | O4: =SUM(B4:M4) -> 0
A5: COUNCIL TAX | B5: 200 | F5: 200 | O5: =SUM(B5:M5) -> 400
A6: TOTAL | B6: =SUM(B3:B5) -> 850 | C6: =SUM(C3:C5) -> 0 | D6: =SUM(D3:D5) -> 0 | E6: =SUM(E3:E5) -> 0 | F6: =SUM(F3:F5) -> 200 | G6: =SUM(G3:G5) -> 0 | H6: =SUM(H3:H5) -> 0 | I6: =SUM(I3:I5) -> 0 | ... M6: =SUM(M3:M5) -> 0 | O6: =SUM(B6:M6) -> 1050
A7: EE | B7: 90 | C7: 90 | D7: 90 | E7: 90 | F7: 90 | G7: 90 | H7: 90 | O7: =SUM(B7:M7) -> 630
A8: VIRGIN | B8: 105 | C8: 105 | D8: 105 | E8: 105 | F8: 105 | G8: 105 | H8: 105 | O8: =SUM(B8:M8) -> 735
A9: ELECTRICITY | B9: 175 | C9: 175 | D9: 175 | E9: 175 | F9: 175 | G9: 175 | H9: 175
A10: ECLECTRICITY ARREARS | B10: 300 | C10: 300 | D10: 300 | E10: 300 | F10: 300 | G10: 300 | H10: 300 | L10: 300 | O10: =SUM(B10:M10) -> 2400
A11: LIFE INSURANCE | B11: 15 | C11: 15 | D11: 15 | E11: 15 | F11: 15 | G11: 15 | H11: 15 | O11: =SUM(B11:M11) -> 105
A12: TOTAL | B12: =SUM(B7:B11) -> 685 | C12: =SUM(C7:C11) -> 685 | D12: =SUM(D7:D11) -> 685 | E12: =SUM(E7:E11) -> 685 | F12: =SUM(F7:F11) -> 685 | G12: =SUM(G7:G11) -> 685 | H12: =SUM(H7:H11) -> 685 | I12: =SUM(I7:I11) -> 0 | ... M12: =SUM(M7:M11) -> 0 | O12: =SUM(B12:M12) -> 5095
A13: UBER | B13: 50 | C13: 50 | D13: 50 | E13: 50 | F13: 50 | G13: 50 | H13: 50 | O13: =SUM(B13:M13) -> 350
A14: TRAVEL | B14: 65 | C14: 65 | D14: 65 | E14: 65 | F14: 65 | G14: 65 | H14: 65 | O14: =SUM(B14:M14) -> 455
A15: FOOD | B15: 250 | C15: 250 | D15: 250 | E15: 250 | F15: 250 | G15: 250 | H15: 250 | O15: =SUM(B15:M15) -> 1750
A16: MY PROTIEN | O16: =SUM(B16:M16) -> 0
A17: LUNCH | B17: 90 | C17: 90 | D17: 90 | E17: 90 | F17: 90 | G17: 90 | H17: 90 | O17: =SUM(B17:M17) -> 630
A18: TAKE AWAY | O18: =SUM(B18:M18) -> 0
A19: MONTHLY ALLOWANCE | B19: 200 | C19: 200 | D19: 200 | E19: 200 | F19: 200 | G19: 200 | H19: 200 | O19: =SUM(B19:M19) -> 1400
A20: LAUNDRY | B20: 20 | C20: 20 | D20: 20 | E20: 20 | F20: 20 | G20: 20 | H20: 20 | O20: =SUM(B20:M20) -> 140
A21: TOTAL | B21: =SUM(B7:B20) -> 2045 | C21: =SUM(C7:C20) -> 2045 | D21: =SUM(D7:D20) -> 2045 | E21: =SUM(E7:E20) -> 2045 | F21: =SUM(F7:F20) -> 2045 | G21: =SUM(G7:G20) -> 2045 | H21: =SUM(H7:H20) -> 2045 | I21: =SUM(I13:I20) -> 0 | J21: =SUM(J13:J20) -> 0 | K21: =SUM(K13:K20) -> 0 | L21: =SUM(L13:L20) -> 0 | M21: =SUM(M13:M20) -> 0 | O21: =SUM(B21:M21) -> 14315
A22: GYM | B22: 30 | C22: 30 | H22: 35 | I22: 30 | O22: =SUM(B22:M22) -> 125
A23: SPLICE | B23: 25 | C23: 10 | F23: 35 | L23: 25
A24: PLUG IN ALLIANCE | B24: 25 | C24: 25 | F24: 25
A25: MICROSOFT | B25: 6 | C25: 6 | L25: 8
A26: LINKTREE | F26: 10
A27: APPLE ITUNES | B27: 12 | C27: 12 | H27: 15 | L27: 15
A28: MAILCHIMP | O28: =SUM(B28:M28) -> 0
A29: DRMS | H29: 5 | L29: 5
A30: SPOTIFY | H30: 15
A31: TOTAL | B31: =SUM(B22:B30) -> 98 | C31: =SUM(C22:C30) -> 83 | D31: =SUM(D22:D30) -> 0 | E31: =SUM(E22:E30) -> 0 | F31: =SUM(F22:F30) -> 70 | G31: =SUM(G22:G30) -> 0 | H31: =SUM(H22:H30) -> 70 | I31: =SUM(I22:I30) -> 30 | ... M31: =SUM(M22:M30) -> 0 | O31: =SUM(B31:M31) -> 404
A32: JAYDA | B32: 180 | C32: 180 | D32: 180 | E32: 180 | F32: 180 | G32: 180 | H32: 180 | O32: =SUM(B32:M32) -> 1260
A33: JAYDA ALLOWANCE | B33: 60 | C33: 60 | D33: 60 | E33: 60 | F33: 60 | G33: 60 | H33: 60 | I33: 45 | L33: 60 | O33: =SUM(B33:M33) -> 525
A34: JAYDA SAVING 2 | O34: =SUM(B34:M34) -> 0
A35: JAYDA EXTRA | B35: 50 | C35: 50 | D35: 50 | E35: 50 | F35: 50 | G35: 50 | H35: 50 | O35: =SUM(B35:M35) -> 350
A36: TOTAL | B36: =SUM(B32:B35) -> 290 | C36: =SUM(C32:C35) -> 290 | D36: =SUM(D32:D35) -> 290 | E36: =SUM(E32:E35) -> 290 | F36: =SUM(F32:F35) -> 290 | G36: =SUM(G32:G35) -> 290 | H36: =SUM(H32:H35) -> 290 | I36: =SUM(I32:I35) -> 45 | ... M36: =SUM(M32:M35) -> 0 | O36: =SUM(B36:M36) -> 2135
A37: VANQUIS | O37: =SUM(B37:M37) -> 0
A38: TOTAL | B38: =SUM(B37:B37) -> 0 | C38: =SUM(C37:C37) -> 0 | D38: =SUM(D37:D37) -> 0 | E38: =SUM(E37:E37) -> 0 | F38: =SUM(F37:F37) -> 0 | G38: =SUM(G37:G37) -> 0 | H38: =SUM(H37:H37) -> 0 | I38: =SUM(I37:I37) -> 0 | ... M38: =SUM(M37:M37) -> 0 | O38: =SUM(B38:M38) -> 0
A39: HOLIDAY FLIGHTS | O39: =SUM(B39:M39) -> 0
A40: BARBERS | B40: 60
A41: HOTEL
A42: BODY CARE | O42: =SUM(B42:M42) -> 0
A43: HOLIDAY MONEY | L43: 1400 | O43: =SUM(B43:M43) -> 1400
A44: CLOTHES /SELF SHOPPING | O44: =SUM(B44:M44) -> 0
A45: EVENT ARREARS | B45: 400 | O45: =SUM(B45:M45) -> 400
A46: OCCASIONS | O46: =SUM(B46:M46) -> 0
A47: MUSIC RELEASE INV | O47: =SUM(B47:M47) -> 0
A48: MUMMY | O48: =SUM(B48:M48) -> 0
A49: DJ MARKETING | O49: =SUM(B49:M49) -> 0
A50: GIFTS | O50: =SUM(B50:M50) -> 0
A51: TOTAL | B51: =SUM(B39:B50) -> 460 | C51: =SUM(C39:C50) -> 0 | D51: =SUM(D39:D50) -> 0 | E51: =SUM(E39:E50) -> 0 | F51: =SUM(F39:F50) -> 0 | G51: =SUM(G39:G50) -> 0 | H51: =SUM(H39:H50) -> 0 | I51: =SUM(I39:I50) -> 0 | ... M51: =SUM(M39:M50) -> 0 | O51: =SUM(B51:M51) -> 1860
O52: =SUM(B52:M52) -> 0
A53: HOME | O53: =SUM(B53:M53) -> 0
A54: EMERGENCY FUNDS | B54: 200 | O54: =SUM(K54:M54) -> 0
A55: SINGLE SAVING | O55: =SUM(B55:M55) -> 0
A56: HOME DEPOSIT | O56: =SUM(B56:M56) -> 0
A57: INVESTMENT | H57: 800 | O57: =SUM(K57:M57) -> 0
A58: TOTAL | B58: =SUM(B52:B57) -> 200 | C58: =SUM(C52:C57) -> 0 | D58: =SUM(D52:D57) -> 0 | E58: =SUM(E52:E56) -> 0 | F58: =SUM(F52:F57) -> 0 | G58: =SUM(G52:G57) -> 0 | H58: =SUM(H52:H57) -> 800 | I58: =SUM(I52:I57) -> 0 | J58: =SUM(J52:J57) -> 0 | K58: =SUM(K52:K57) -> 0 | L58: =SUM(L52:L57) -> 0 | M58: =SUM(M52:M57) -> 0 | O58: =SUM(B58:M58) -> 1000
A61: TOTAL | B61: =SUM(B6+B21+B31+B36+B38+B51+B58) -> 3943 | C61: =SUM(C6+C21+C31+C36+C38+C51+C58) -> 2418 | D61: =SUM(D6+D21+D31+D36+D38+D51+D58) -> 2335 | F61: =SUM(F6+F21+F31+F36+F38+F51+F58) -> 2605 | G61: =SUM(G6+G21+G31+G36+G38+G51+G58) -> 2335 | H61: =SUM(H6+H21+H31+H36+H38+H51+H58) -> 3205 | K61: =SUM(K6+K12+K21+K31+K36+K38+K51+K58) -> 0 | M61: =SUM(M6+M12+M21+M31+M36+M38+M51+M58) -> 0 | O61: =SUM(B61:M61) -> 16841
A62: SALARY | B62: 3870 | C62: 250 | D62: 338 | F62: 605 | G62: 892 | H62: 230 | O62: =SUM(B62:M62) -> 6185
A63: MY EVENTS | B63: 900 | C63: 625 | H63: 425 | O63: =SUM(B63:M63) -> 1950
A64: PRODUCTION | F64: 200 | G64: 340 | H64: 200
A65: DJ GIGS | B65: 1070 | C65: 90 | D65: 300 | O65: =SUM(B65:M65) -> 1460
A66: HOUSE MATE | B66: 450 | F66: 450 | O66: =SUM(B66:M66) -> 900
A67: MADE | B67: =SUM(B62:B66) -> 6290 | C67: =SUM(C62:C66) -> 965 | D67: =SUM(D62:D66) -> 638 | E67: =SUM(E62:E66) -> 0 | F67: =SUM(F62:F66) -> 1255 | G67: =SUM(G62:G66) -> 1232 | H67: =SUM(H62:H66) -> 855 | K67: =SUM(K62:K66) -> 0 | O67: =SUM(B67:M67) -> 11235
A68: EXTRA | C68: =(C67-C61) -> -1453 | F68: =(F67-F61) -> -1350 | G68: =(G67-G61) -> -1103 | O68: =SUM(I68:M68) -> 0
L69: YEAR END | O69: =SUM(O3:O68) -> 78135
L71: TOTAL UNTOUCHED | O71: =SUM(B58:M58) -> 1000
L72: SAVINGS | O72: =SUM(I68:M68) -> 0

Sheet PERSONAL BUDGET 2023-2024
A1: 2022 | B1: AUGUST | C1: SEPTEMBER | D1: OCTOBER | E1: NOVEMBER | F1: DECEMBER | G1: JANUARY | H1: FEBURARY | I1: MARCH | J1: APRIL | K1: MAY | L1: JUNE | M1: JULY | O1: TOTAL
A3: RENT | O3: =SUM(B3:M3) -> 0
A4: STUDIO RENT | O4: =SUM(B4:M4) -> 0
A5: COUNCIL TAX | O5: =SUM(B5:M5) -> 0
A6: TOTAL | B6: =SUM(B3:B5) -> 0 | C6: =SUM(C3:C5) -> 0 | D6: =SUM(D3:D5) -> 0 | E6: =SUM(E3:E5) -> 0 | F6: =SUM(F3:F5) -> 0 | H6: =SUM(H3:H5) -> 0 | I6: =SUM(I3:I5) -> 0 | J6: =SUM(J3:J5) -> 0 | K6: =SUM(K3:K5) -> 0 | L6: =SUM(L3:L5) -> 0 | M6: =SUM(M3:M5) -> 0 | O6: =SUM(B6:M6) -> 0
A7: EE | H7: 90 | O7: =SUM(B7:M7) -> 90
A8: VIRGIN | O8: =SUM(B8:M8) -> 0
A9: ECLECTRICITY | B9: 100 | H9: 130 | O9: =SUM(B9:M9) -> 230
A10: LIFE INSURANCE | H10: 15 | O10: =SUM(B10:M10) -> 15
B11: =SUM(B7:B10) -> 100 | C11: =SUM(C7:C10) -> 0 | D11: =SUM(D7:D10) -> 0 | E11: =SUM(E7:E10) -> 0 | F11: =SUM(F7:F10) -> 0 | G11: =SUM(G7:G10) -> 0 | H11: =SUM(H7:H10) -> 235 | I11: =SUM(I7:I10) -> 0 | ... M11: =SUM(M7:M10) -> 0 | O11: =SUM(B11:M11) -> 335
A12: UBER | O12: =SUM(B12:M12) -> 0
A13: TRAVEL | O13: =SUM(B13:M13) -> 0
A14: FOOD | O14: =SUM(B14:M14) -> 0
A15: LUNCH | O15: =SUM(B15:M15) -> 0
A16: MONTHLY ALLOWANCE | O16: =SUM(B16:M16) -> 0
A17: PERSONAL TRAINER | O17: =SUM(B17:M17) -> 0
B18: =SUM(B12:B17) -> 0 | C18: =SUM(C12:C17) -> 0 | D18: =SUM(D12:D17) -> 0 | E18: =SUM(E12:E17) -> 0 | F18: =SUM(F12:F17) -> 0 | G18: =SUM(G12:G17) -> 0 | H18: =SUM(H12:H17) -> 0 | I18: =SUM(I12:I17) -> 0 | ... M18: =SUM(M12:M17) -> 0 | O18: =SUM(B18:M18) -> 0
A19: GYM | O19: =SUM(B19:M19) -> 0
A20: SERVER | O20: =SUM(B20:M20) -> 0
A21: SPLICE | B21: 10 | H21: 8 | O21: =SUM(B21:M21) -> 18
A22: SPOTIFY | B22: 15 | H22: 20
A23: PLUG IN ALLIANCE | H23: 15 | O23: =SUM(B23:M23) -> 15
A24: MICROSOFT | O24: =SUM(B24:M24) -> 0
A25: APPLE ITUNES | B25: 12 | H25: 12 | O25: =SUM(B25:M25) -> 24
A26: MixWMasters | B26: 5 | H26: 25 | O26: =SUM(B26:M26) -> 30
A27: ADOBE | O27: =SUM(B27:M27) -> 0
A28: TOTAL | B28: =SUM(B19:B27) -> 42 | C28: =SUM(C19:C27) -> 0 | D28: =SUM(D19:D27) -> 0 | E28: =SUM(E19:E27) -> 0 | F28: =SUM(F19:F27) -> 0 | H28: =SUM(H19:H27) -> 80 | I28: =SUM(I19:I27) -> 0 | J28: =SUM(J19:J27) -> 0 | K28: =SUM(K19:K27) -> 0 | L28: =SUM(L19:L27) -> 0 | M28: =SUM(M19:M27) -> 0 | O28: =SUM(B28:M28) -> 122
A29: JAYDA | O29: =SUM(B29:M29) -> 0
A30: JAYDA ALLOWANCE | B30: 60 | C30: 40 | H30: 100 | O30: =SUM(B30:M30) -> 200
A31: JAYDA SAVING 2 | O31: =SUM(B31:M31) -> 0
A32: JAYDA FRENCH | O32: =SUM(B32:M32) -> 0
A33: JAYDA DANCE | O33: =SUM(B33:M33) -> 0
A34: JAYDA HOLIDAY
A35: JAYDA SCHOOL GEAR
A36: JAYDA CLOTHES
A37: TOTAL | E37: =SUM(E29:E36) -> 0 | O37: =SUM(B37:M37) -> 0
A38: FAMILY
A41: TOTAL | E41: =SUM(E38:E40) -> 0 | F41: =SUM(F38:F40) -> 0 | G41: =SUM(G38:G40) -> 0 | H41: =SUM(H38:H40) -> 0 | I41: =SUM(I38:I40) -> 0 | J41: =SUM(J38:J40) -> 0 | K41: =SUM(K38:K40) -> 0 | L41: =SUM(L38:L40) -> 0 | M41: =SUM(M29:M40) -> 0
A42: TANA
A43: MUMMY
A44: MUMMY | B44: =SUM(B29:B43) -> 60 | C44: =SUM(C29:C43) -> 40 | D44: =SUM(D29:D43) -> 0 | E44: =SUM(E42:E43) -> 0 | F44: =SUM(F42:F43) -> 0 | G44: =SUM(G42:G43) -> 0 | H44: =SUM(H42:H43) -> 0 | I44: =SUM(I42:I43) -> 0 | J44: =SUM(J42:J43) -> 0 | K44: =SUM(K42:K43) -> 0 | L44: =SUM(L42:L43) -> 0 | M44: =SUM(M42:M43) -> 0 | O44: =SUM(B44:M44) -> 100
A45: VANQUIS | O45: =SUM(B45:M45) -> 0
A46: TOTAL | B46: =SUM(B45:B45) -> 0 | C46: =SUM(C45:C45) -> 0 | D46: =SUM(D45:D45) -> 0 | E46: =SUM(E45:E45) -> 0 | F46: =SUM(F45:F45) -> 0 | G46: =SUM(G45:G45) -> 0 | H46: =SUM(H45:H45) -> 0 | I46: =SUM(I45:I45) -> 0 | ... M46: =SUM(M45:M45) -> 0 | O46: =SUM(B46:M46) -> 0
A47: BARBERS
A48: BODY CARE | K48: 100 | O48: =SUM(B48:M48) -> 100
A49: PRODUCTION
A50: CLOTHES | O50: =SUM(B50:M50) -> 0
A51: HOTEL | O51: =SUM(B51:M51) -> 0
A52: TRAVEL SPENDING
A53: FLIGHTS
A54: TRAIN
A55: OCCASIONS | O55: =SUM(B55:M55) -> 0
A56: GIFTS | O56: =SUM(B56:M56) -> 0
A57: TOTAL | B57: =SUM(B47:B56) -> 0 | C57: =SUM(C47:C56) -> 0 | D57: =SUM(D47:D56) -> 0 | E57: =SUM(E47:E56) -> 0 | F57: =SUM(F47:F56) -> 0 | G57: =SUM(G47:G56) -> 0 | H57: =SUM(H47:H56) -> 0 | I57: =SUM(I47:I56) -> 0 | J57: =SUM(J47:J56) -> 0 | L57: =SUM(L47:L56) -> 0 | M57: =SUM(M47:M56) -> 0 | O57: =SUM(B57:M57) -> 0
O58: =SUM(B58:M58) -> 0
A59: HOME | O59: =SUM(B59:M59) -> 0
A60: EMERGENCY FUNDS | O60: =SUM(B60:M60) -> 0
A61: SINGLE SAVING | O61: =SUM(B61:M61) -> 0
A62: HOME DEPOSIT | O62: =SUM(B62:M62) -> 0
A63: INVESTMENT | O63: =SUM(B63:M63) -> 0
A64: TOTAL | B64: =SUM(B58:B63) -> 0 | C64: =SUM(C58:C63) -> 0 | D64: =SUM(D58:D63) -> 0 | E64: =SUM(E58:E63) -> 0 | F64: =SUM(F58:F63) -> 0 | G64: 2 | H64: =SUM(H58:H63) -> 0 | I64: =SUM(I58:I63) -> 0 | J64: =SUM(J58:J63) -> 0 | K64: =SUM(K58:K63) -> 0 | L64: =SUM(L58:L63) -> 0 | O64: =SUM(B64:M64) -> 2
A67: TOTAL | D67: =SUM(D6+D11+D18+D28+D44+D46+D57+D64) -> 0 | F67: =SUM(F6+F11+F18+F28+F37+F41+F44+F46+F57+F64) -> 0 | H67: =SUM(H6+H11+H18+H28+H37+H41+H44+H46+H57+H64) -> 315 | I67: =SUM(I6+I11+I18+I28+I37+I41+I44+I46+I57+I64) -> 0 | J67: =SUM(J6+J11+J18+J28+J37+J41+J44+J46+J57+J64) -> 0 | K67: =SUM(K6+K11+K18+K28+K37+K41+K44+K46+K57+K64) -> 0 | L67: =SUM(L6+L11+L18+L28+L37+L41+L44+L46+L57+L64) -> 0 | M67: =SUM(M6+M11+M18+M28+M37+M41+M44+M46+M57+M64) -> 0 | O67: =SUM(B67:M67) -> 315
A68: SALARY | B68: 690 | H68: 270 | O68: =SUM(B68:M68) -> 960
A69: MY EVENTS | O69: =SUM(B69:M69) -> 0
A70: PRODUCTION | H70: 125
A71: GIGS | H71: 250 | O71: =SUM(B71:M71) -> 250
A72: LENDING
A73: TANA
A74: BRAVO | H74: 475 | O74: =SUM(B74:M74) -> 475
A75: MADE | C75: =SUM(C68:C74) -> 0 | D75: =SUM(D68:D74) -> 0 | F75: =SUM(F68:F74) -> 0 | H75: =SUM(H68:H74) -> 1120 | I75: =SUM(I68:I74) -> 0 | J75: =SUM(J68:J74) -> 0 | K75: =SUM(K68:K74) -> 0 | M75: =SUM(M68:M74) -> 0 | O75: =SUM(B75:M75) -> 1120
A76: EXTRA | F76: \ | M76: =(M75-M67-M63) -> 0 | O76: =SUM(B76:M76) -> 0
L77: YEAR END | O77: =SUM(O3:O76) -> 4401
L79: TOTAL UNTOUCHED | O79: =SUM(B64:M64) -> 2
L80: SAVINGS | O80: =SUM(B76:M76) -> 0

Sheet PERSONAL BUDGET 2024-2025
A1: 2025 | B1: AUGUST | C1: SEPTEMBER | D1: OCTOBER | E1: NOVEMBER | F1: DECEMBER | G1: JANUARY | H1: FEBURARY | I1: MARCH | J1: APRIL | K1: MAY | L1: JUNE | M1: JULY | O1: TOTAL
A3: RENT | O3: =SUM(B3:M3) -> 0
A4: STUDIO RENT | O4: =SUM(B4:M4) -> 0
A5: COUNCIL TAX | O5: =SUM(B5:M5) -> 0
A6: TOTAL | B6: =SUM(B3:B5) -> 0 | C6: =SUM(C3:C5) -> 0 | D6: =SUM(D3:D5) -> 0 | E6: =SUM(E3:E5) -> 0 | F6: =SUM(F3:F5) -> 0 | G6: =SUM(G3:G5) -> 0 | H6: =SUM(H3:H5) -> 0 | I6: =SUM(I3:I5) -> 0 | J6: =SUM(J3:J5) -> 0 | L6: =SUM(L3:L5) -> 0 | M6: =SUM(M3:M5) -> 0 | O6: =SUM(B6:M6) -> 0
A7: EE | J7: 55 | O7: =SUM(B7:M7) -> 55
A8: SKY | O8: =SUM(B8:M8) -> 0
A9: ECLECTRICITY | J9: 65 | O9: =SUM(B9:M9) -> 65
A10: APPLICANE INSURANCE | O10: =SUM(B10:M10) -> 0
A11: ZURICH LIFE INSURANCE | O11: =SUM(B11:M11) -> 0
A12: THAMESWATER | O12: =SUM(B12:M12) -> 0
A13: LIFE INSURANCE | J13: 15 | O13: =SUM(B13:M13) -> 15
B14: =SUM(B7:B13) -> 0 | C14: =SUM(C7:C13) -> 0 | D14: =SUM(D7:D13) -> 0 | E14: =SUM(E7:E13) -> 0 | F14: =SUM(F7:F13) -> 0 | G14: =SUM(G7:G13) -> 0 | H14: =SUM(H7:H13) -> 0 | I14: =SUM(I7:I13) -> 0 | J14: =SUM(J7:J13) -> 135 | L14: =SUM(L7:L13) -> 0 | M14: =SUM(M7:M13) -> 0
A15: UBER | J15: 50 | M15: 10 | O15: =SUM(B15:M15) -> 60
A16: TRAVEL | I16: 120 | J16: 120 | L16: 50 | M16: 100 | O16: =SUM(B16:M16) -> 390
A17: FOOD | I17: 150 | J17: 150 | L17: 70 | M17: 60 | O17: =SUM(B17:M17) -> 430
A18: MY PROTIEN
A19: LUNCH | I19: 100 | J19: 100 | L19: 50 | M19: 70 | O19: =SUM(B19:M19) -> 320
A20: MONTHLY ALLOWANCE | I20: 100 | J20: 400 | M20: 300 | O20: =SUM(B20:M20) -> 800
A21: PERSONAL TRAINER | O21: =SUM(B21:M21) -> 0
B22: =SUM(B15:B21) -> 0 | C22: =SUM(C15:C21) -> 0 | D22: =SUM(D15:D21) -> 0 | E22: =SUM(E15:E21) -> 0 | F22: =SUM(F15:F21) -> 0 | G22: =SUM(G15:G21) -> 0 | H22: =SUM(H15:H21) -> 0 | I22: =SUM(I15:I21) -> 470 | J22: =SUM(J15:J21) -> 820 | L22: =SUM(L15:L21) -> 170 | M22: =SUM(M15:M21) -> 540
A23: GYM | I23: 40 | J23: 40 | O23: =SUM(B23:M23) -> 80
A24: SPLICE | J24: 10
A25: SITE GROUND | J25: 50
A26: SPOTIFY | J26: 20
A27: SLATE | J27: 14 | M27: 14
A28: LINKTREE | M28: 5
A29: PLUG IN ALLIANCE
A30: MICROSOFT | I30: 8 | J30: 10 | L30: 6 | M30: 6
A31: APPLE ITUNES | J31: 12
A32: SERATO | I32: 10 | J32: 10 | M32: 10
A33: EXPERIAN | I33: 15 | J33: 15
A34: SNOOP | I34: 5 | J34: 5
A35: OPEN AI
A36: MONZO | I36: 15 | J36: 15 | O36: =SUM(B36:M36) -> 30
A37: REVOLUT | I37: 55 | J37: 55 | L37: 55 | M37: 55 | O37: =SUM(B37:M37) -> 220
A38: TOTAL | B38: =SUM(B23:B37) -> 0 | C38: =SUM(C23:C37) -> 0 | D38: =SUM(D23:D37) -> 0 | E38: =SUM(E23:E37) -> 0 | F38: =SUM(F23:F37) -> 0 | G38: =SUM(G23:G37) -> 0 | H38: =SUM(H23:H37) -> 0 | I38: =SUM(I23:I37) -> 148 | ... M38: =SUM(M23:M37) -> 90 | O38: =SUM(B38:M38) -> 555
A39: JAYDA | O39: =SUM(B39:M39) -> 0
A40: JAYDA ALLOWANCE | J40: 120 | O40: =SUM(B40:M40) -> 120
A41: JAYDA SAVING 2 | O41: =SUM(B41:M41) -> 0
A42: JAYDA FRENCH | O42: =SUM(B42:M42) -> 0
A43: JAYDA DANCE | O43: =SUM(B43:M43) -> 0
A44: JAYDA HOLIDAY
A45: JAYDA SCHOOL GEAR | O45: =SUM(B45:M45) -> 0
A46: TOTAL | B46: =SUM(B39:B45) -> 0 | C46: =SUM(C39:C45) -> 0 | D46: =SUM(D39:D45) -> 0 | E46: =SUM(E39:E45) -> 0 | F46: =SUM(F39:F45) -> 0 | G46: =SUM(G39:G45) -> 0 | H46: =SUM(H39:H45) -> 0 | I46: =SUM(I39:I45) -> 0 | ... M46: =SUM(M39:M45) -> 0 | O46: =SUM(B46:M46) -> 120
A47: AUDIO GEAR | I47: 175 | J47: 175 | M47: 175 | O47: =SUM(B47:M47) -> 525
A48: DISTROKID | O48: =SUM(B48:M48) -> 0
A49: CARD | O49: =SUM(B49:M49) -> 0
A50: TOTAL | B50: =SUM(B49:B49) -> 0 | C50: =SUM(C49:C49) -> 0 | D50: =SUM(D49:D49) -> 0 | E50: =SUM(E49:E49) -> 0 | F50: =SUM(F49:F49) -> 0 | G50: =SUM(G47:G49) -> 0 | H50: =SUM(H47:H49) -> 0 | I50: =SUM(I47:I49) -> 175 | J50: =SUM(J47:J49) -> 175 | K50: =SUM(K47:K49) -> 0 | L50: =SUM(L47:L49) -> 0 | M50: =SUM(M47:M49) -> 175 | O50: =SUM(B50:M50) -> 525
A51: BARBERS
A52: BODY CARE | K52: 100 | O52: =SUM(B52:M52) -> 100
A53: CLOTHES | O53: =SUM(B53:M53) -> 0
A54: PRODUCTION
A55: HOLIDAY
A56: OTHER
A57: OCCASIONS | O57: =SUM(B57:M57) -> 0
A58: GIFTS | O58: =SUM(B58:M58) -> 0
A59: TOTAL | B59: =SUM(B51:B58) -> 0 | C59: =SUM(C51:C58) -> 0 | D59: =SUM(D51:D58) -> 0 | E59: =SUM(E51:E58) -> 0 | F59: =SUM(F51:F58) -> 0 | G59: =SUM(G51:G58) -> 0 | H59: =SUM(H51:H58) -> 0 | I59: =SUM(I51:I58) -> 0 | J59: =SUM(J51:J58) -> 0 | L59: =SUM(L51:L58) -> 0 | M59: =SUM(M51:M58) -> 0 | O59: =SUM(B59:M59) -> 0
O60: =SUM(B60:M60) -> 0
A61: HOME APPLIANCES AND DÉCOR | O61: =SUM(B61:M61) -> 0
A62: EMERGENCY FUNDS | O62: =SUM(B62:M62) -> 0
A63: SINGLE SAVING | O63: =SUM(B63:M63) -> 0
A64: HOME DEPOSIT | G64: 12600
A65: INVESTMENT | O65: =SUM(B65:M65) -> 0
A66: TOTAL | B66: =SUM(B60:B64) -> 0 | C66: =SUM(C60:C64) -> 0 | D66: =SUM(D60:D64) -> 0 | E66: =SUM(E60:E64) -> 0 | F66: =SUM(F60:F64) -> 0 | G66: =SUM(G60:G65) -> 12600 | H66: =SUM(H60:H64) -> 0 | I66: =SUM(I60:I64) -> 0 | J66: =SUM(J60:J64) -> 0 | K66: =SUM(K60:K64) -> 0 | L66: =SUM(L60:L64) -> 0 | M66: =SUM(M60:M64) -> 0 | O66: =SUM(B66:M66) -> 12600
A69: TOTAL | C69: =SUM(C6+C14+C22+C38+C46+C50+C59+C66) -> 0 | D69: =SUM(D6+D14+D22+D38+D46+D50+D59+D66) -> 0 | E69: =SUM(E6+E14+E22+E38+E46+E50+E59+E66) -> 0 | G69: =SUM(G6+G14+G22+G38+G46+G50+G59+G66) -> 12600 | K69: =SUM(K6+K14+K22+K38+K46+K50+K59+K66) -> 0 | M69: =SUM(M6+M14+M22+M38+M46+M50+M59+M66) -> 805 | O69: =SUM(B69:M69) -> 13405
A70: SALARY | M70: 400 | O70: =SUM(B70:M70) -> 400
A71: PRODUCTION
A72: MY EVENTS | M72: 150 | O72: =SUM(B72:M72) -> 150
A73: GIGS | M73: 240 | O73: =SUM(B73:M73) -> 240
A74: MISC | M74: 100 | O74: =SUM(B74:M74) -> 100
A75: MADE | B75: =SUM(B70:B74) -> 0 | C75: =SUM(C70:C74) -> 0 | D75: =SUM(D70:D74) -> 0 | E75: =SUM(E70:E74) -> 0 | H75: =SUM(H70:H74) -> 0 | I75: =SUM(I70:I74) -> 0 | J75: =SUM(J70:J74) -> 0 | K75: =SUM(K70:K74) -> 0 | L75: =SUM(L70:L74) -> 0 | M75: =SUM(M70:M74) -> 890 | O75: =SUM(B75:M75) -> 890
A76: EXTRA SAVING | B76: =(B75-B69) -> 0 | C76: =(C75-C69) -> 0 | D76: =(D75-D69) -> 0 | E76: =(E75-E69) -> 0 | F76: =(F75-F69) -> 0 | H76: =(H75-H69) -> 0 | I76: =(I75-I69) -> 0 | J76: =(J75-J69) -> 0 | K76: =(K75-K69) -> 0 | L76: =(L75-L69) -> 0 | M76: =(M75-M69-'[1]House DECO & REPAIR 25'!$B$32) -> 85 | O76: =SUM(B76:M76) -> 85
L77: YEAR END | O77: =SUM(O3:O76) -> 32280
L79: TOTAL UNTOUCHED | O79: =SUM(B66:M66) -> 12600
L80: SAVINGS | O80: =SUM(B76:M76) -> 85

Sheet PERSONAL BUDGET 2025-2026
A1: 2025 - 2026 | B1: AUGUST | C1: SEPTEMBER | D1: OCTOBER | E1: NOVEMBER | F1: DECEMBER | G1: JANUARY | I1: FEBURARY | K1: MARCH | M1: APRIL | O1: MAY | Q1: JUNE | S1: JULY | U1: YEAR TOTAL
A3: HOUSING COSTS
A4: RENT | G4: 800 | H4: Not Paid | I4: 1090 | J4: Not Paid | K4: 1090 | L4: Not Paid | M4: 1090 | N4: Not Paid | O4: 1025 | P4: Not Paid | Q4: 1025 | R4: Not Paid | S4: 1175 | U4: =SUM(B4:S4) -> 7295
A5: MORTGAGE | G5: 750 | H5: Paid | I5: 750 | J5: Not Paid | K5: 750 | L5: Not Paid | M5: 750 | N5: Not Paid | O5: 825 | P5: Not Paid | Q5: 825 | R5: Not Paid | S5: 825 | U5: =SUM(B5:S5) -> 5475
A6: COUNCIL TAX | G6: 166 | H6: Not Paid | I6: 166 | J6: Not Paid | K6: 170 | L6: Not Paid | M6: 170 | N6: Not Paid | O6: 170 | P6: Not Paid | Q6: 170 | R6: Not Paid | S6: 170 | U6: =SUM(B6:S6) -> 1182
A7: HONE DECO / REPAIR | C7: =SUM('[1]House DECO & REPAIR 25'!$D$32) -> 0 | G7: 0 | H7: Not Paid | I7: 0 | J7: Not Paid | K7: 0 | L7: Not Paid | M7: 0 | N7: Not Paid | O7: 0 | P7: Not Paid | Q7: 0 | R7: Not Paid | U7: =SUM(B7:S7) -> 0
A8: SUB TOTAL | B8: =SUM(B4:B7) -> 0 | C8: =SUM(C4:C7) -> 0 | D8: =SUM(D4:D7) -> 0 | E8: =SUM(E4:E7) -> 0 | F8: =SUM(F4:F7) -> 0 | G8: =SUM(G4:G7) -> 1716 | I8: =SUM(I4:I7) -> 2006 | K8: =SUM(K4:K7) -> 2010 | M8: =SUM(M4:M7) -> 2010 | O8: =SUM(O4:O7) -> 2020 | Q8: =SUM(Q4:Q7) -> 2020 | S8: =SUM(S4:S7) -> 2170 | U8: =SUM(U4:U7) -> 13952
A9: UTILITIES
A10: EE | G10: 72 | H10: Not Paid | I10: 72 | J10: Not Paid | K10: 72 | L10: Not Paid | M10: 72 | N10: Not Paid | O10: 72 | P10: Not Paid | Q10: 72 | R10: Not Paid | S10: 72 | U10: =SUM(B10:S10) -> 504
A11: SKY | G11: 105 | H11: Paid | I11: 105 | J11: Not Paid | K11: 105 | L11: Not Paid | M11: 105 | N11: Not Paid | O11: 105 | P11: Not Paid | Q11: 105 | R11: Not Paid | S11: 105 | U11: =SUM(B11:S11) -> 735
A12: ECLECTRICITY | H12: Not Paid | I12: 70 | J12: Not Paid | K12: 70 | L12: Not Paid | M12: 70 | N12: Not Paid | O12: 70 | P12: Not Paid | Q12: 70 | R12: Not Paid | S12: 70 | U12: =SUM(B12:S12) -> 420
A13: THAMES WATER | G13: 40 | H13: Paid | I13: 40 | J13: Not Paid | K13: 40 | L13: Not Paid | M13: 40 | N13: Not Paid | O13: 40 | P13: Not Paid | Q13: 40 | R13: Not Paid | S13: 40 | U13: =SUM(B13:S13) -> 280
A14: ZURICH | G14: 15 | H14: Not Paid | I14: 15 | J14: Not Paid | K14: 15 | L14: Not Paid | M14: 15 | N14: Not Paid | O14: 15 | P14: Not Paid | Q14: 15 | R14: Not Paid | S14: 15 | U14: =SUM(B14:S14) -> 105
A15: GAS | G15: 50 | H15: Paid | I15: 50 | J15: Not Paid | K15: 50 | L15: Not Paid | M15: 30 | N15: Not Paid | O15: 30 | P15: Not Paid | Q15: 30 | R15: Not Paid | S15: 30 | U15: =SUM(B15:S15) -> 270
A16: APPLICANE INSURANCE | G16: 25 | H16: Paid | I16: 25 | J16: Not Paid | K16: 25 | L16: Not Paid | M16: 25 | N16: Not Paid | O16: 25 | P16: Not Paid | Q16: 25 | R16: Not Paid | S16: 25 | U16: =SUM(B16:S16) -> 175
A17: LIFE INSURANCE | G17: 15 | H17: Not Paid | I17: 15 | J17: Not Paid | K17: 15 | L17: Not Paid | M17: 15 | N17: Not Paid | O17: 15 | P17: Not Paid | Q17: 15 | R17: Not Paid | S17: 15 | U17: =SUM(B17:S17) -> 105
A18: SUB TOTAL | B18: =SUM(B10:B17) -> 0 | C18: =SUM(C10:C17) -> 0 | D18: =SUM(D10:D17) -> 0 | E18: =SUM(E10:E17) -> 0 | F18: =SUM(F10:F17) -> 0 | G18: =SUM(G10:G17) -> 322 | I18: =SUM(I10:I17) -> 392 | K18: =SUM(K10:K17) -> 392 | M18: =SUM(M10:M17) -> 372 | O18: =SUM(O10:O17) -> 372 | Q18: =SUM(Q10:Q17) -> 372 | S18: =SUM(S10:S17) -> 372 | U18: =SUM(U10:U17) -> 2594
A19: ALLOWANCES
A20: WORK TRAVEL | G20: 60 | H20: Not Paid | I20: 60 | J20: Not Paid | K20: 60 | L20: Not Paid | M20: 60 | N20: Not Paid | O20: 60 | P20: Not Paid | Q20: 60 | R20: Not Paid | S20: 60 | U20: =SUM(B20:S20) -> 420
A21: UBER | G21: 20 | H21: Not Paid | I21: 20 | J21: Not Paid | K21: 20 | L21: Not Paid | M21: 20 | N21: Not Paid | O21: 20 | P21: Not Paid | Q21: 20 | R21: Not Paid | S21: 20 | U21: 20
A22: FOOD | G22: 200 | H22: Not Paid | I22: 200 | J22: Not Paid | K22: 200 | L22: Not Paid | M22: 200 | N22: Not Paid | O22: 300 | P22: Not Paid | Q22: 300 | R22: Not Paid | S22: 300 | U22: =SUM(B22:S22) -> 1700
A23: LUNCH | G23: 70 | H23: Not Paid | I23: 70 | J23: Not Paid | K23: 70 | L23: Not Paid | M23: 70 | N23: Not Paid | O23: 70 | P23: Not Paid | Q23: 70 | R23: Not Paid | S23: 70 | U23: =SUM(B23:S23) -> 490
A24: MONTHLY ALLOWANCE | G24: 200 | H24: Not Paid | I24: 150 | J24: Not Paid | K24: 150 | L24: Not Paid | M24: 280 | N24: Not Paid | O24: 100 | P24: Not Paid | Q24: 100 | R24: Not Paid | S24: 100 | U24: =SUM(B24:S24) -> 1080
A25: SUB TOTAL | B25: =SUM(B20:B24) -> 0 | C25: =SUM(C20:C24) -> 0 | D25: =SUM(D20:D24) -> 0 | E25: =SUM(E20:E24) -> 0 | F25: =SUM(F20:F24) -> 0 | G25: =SUM(G20:G24) -> 550 | I25: =SUM(I20:I24) -> 500 | K25: =SUM(K20:K24) -> 500 | M25: =SUM(M20:M24) -> 630 | O25: =SUM(O20:O24) -> 550 | Q25: =SUM(Q20:Q24) -> 550 | S25: =SUM(S20:S24) -> 550 | U25: =SUM(U20:U24) -> 3710
A26: SUBSCRIPTIONS
A27: GYM | G27: 0 | H27: Not Paid | I27: 0 | J27: Not Paid | K27: 0 | L27: Not Paid | M27: 0 | N27: Not Paid | O27: 0 | P27: Not Paid | R27: Not Paid | U27: =SUM(B27:S27) -> 0
A28: SERATO | G28: 10 | H28: Not Paid | I28: 10 | J28: Not Paid | K28: 10 | L28: Not Paid | M28: 10 | N28: Not Paid | O28: 10 | P28: Not Paid | Q28: 10 | R28: Not Paid | S28: 10 | U28: =SUM(B28:S28) -> 70
A29: SPLICE | G29: 10 | H29: Not Paid | I29: 10 | J29: Not Paid | K29: 10 | L29: Not Paid | M29: 10 | N29: Not Paid | O29: 10 | P29: Not Paid | Q29: 10 | R29: Not Paid | S29: 10 | U29: =SUM(B29:S29) -> 70
A30: SITE GROUND | G30: 50 | H30: Not Paid | I30: 50 | J30: Not Paid | K30: 50 | L30: Not Paid | M30: 50 | N30: Not Paid | O30: 50 | P30: Not Paid | Q30: 50 | R30: Not Paid | S30: 50 | U30: =SUM(B30:S30) -> 350
A31: DISNEY PLUS | G31: 5 | H31: Not Paid | I31: 5 | J31: Not Paid | K31: 5 | L31: Not Paid | M31: 5 | N31: Not Paid | O31: 5 | P31: Not Paid | Q31: 5 | R31: Not Paid | S31: 5 | U31: =SUM(B31:S31) -> 35
A32: NETFLIX | G32: 20 | H32: Not Paid | I32: 20 | J32: Not Paid | K32: 20 | L32: Not Paid | M32: 20 | N32: Not Paid | O32: 15 | P32: Not Paid | Q32: 15 | R32: Not Paid | S32: 15 | U32: =SUM(B32:S32) -> 125
A33: SPOTIFY | G33: 20 | H33: Not Paid | I33: 20 | J33: Not Paid | K33: 20 | L33: Not Paid | M33: 20 | N33: Not Paid | O33: 20 | P33: Not Paid | Q33: 20 | R33: Not Paid | S33: 20 | U33: =SUM(B33:S33) -> 140
A34: MICROSOFT | G34: 10 | H34: Not Paid | I34: 10 | J34: Not Paid | K34: 10 | L34: Not Paid | M34: 10 | N34: Not Paid | O34: 10 | P34: Not Paid | Q34: 10 | R34: Not Paid | S34: 10 | U34: =SUM(B34:S34) -> 70
A35: APPLE ITUNES | G35: 12 | H35: Not Paid | I35: 12 | J35: Not Paid | K35: 12 | L35: Not Paid | M35: 12 | N35: Not Paid | O35: 12 | P35: Not Paid | Q35: 12 | R35: Not Paid | S35: 12 | U35: =SUM(B35:S35) -> 84
A36: REVOLUT | G36: 14 | H36: Not Paid | I36: 14 | J36: Not Paid | K36: 14 | L36: Not Paid | M36: 14 | N36: Not Paid | O36: 8 | P36: Not Paid | Q36: 8 | R36: Not Paid | S36: 8 | U36: =SUM(B36:S36) -> 80
A37: SUB TOTAL | B37: =SUM(B27:B36) -> 0 | C37: =SUM(C27:C36) -> 0 | D37: =SUM(D27:D36) -> 0 | E37: =SUM(E27:E36) -> 0 | F37: =SUM(F27:F36) -> 0 | G37: =SUM(G27:G36) -> 151 | I37: =SUM(I27:I36) -> 151 | K37: =SUM(K27:K36) -> 151 | M37: =SUM(M27:M36) -> 151 | O37: =SUM(O27:O36) -> 140 | Q37: =SUM(Q27:Q36) -> 140 | S37: =SUM(S27:S36) -> 140 | U37: =SUM(U27:U36) -> 1024
A38: CHILDCARE
A39: JAYDA | G39: 180 | H39: Paid | I39: 180 | J39: Not Paid | K39: 180 | L39: Not Paid | M39: 180 | N39: Not Paid | O39: 180 | P39: Not Paid | Q39: 180 | R39: Not Paid | S39: 180 | U39: =SUM(B39:S39) -> 1260
A40: JAYDA ALLOWANCE | G40: 100 | H40: Paid | I40: 100 | J40: Not Paid | K40: 100 | L40: Not Paid | M40: 100 | N40: Not Paid | O40: 100 | P40: Not Paid | Q40: 100 | R40: Not Paid | S40: 100 | U40: =SUM(B40:S40) -> 700
A41: JAYDA SAVING 2 | G41: 50 | H41: Paid | I41: 50 | J41: Not Paid | K41: 50 | L41: Not Paid | M41: 50 | N41: Not Paid | O41: 50 | P41: Not Paid | Q41: 50 | R41: Not Paid | S41: 50 | U41: =SUM(B41:S41) -> 350
A42: JAYDA HOLIDAY | G42: 0 | H42: Not Paid | J42: Not Paid | L42: Not Paid | N42: Not Paid | R42: Not Paid | U42: =SUM(B42:S42) -> 0
A43: JAYDA SCHOOL | G43: 0 | H43: Not Paid | J43: Not Paid | L43: Not Paid | N43: Not Paid | R43: Not Paid | U43: =SUM(B43:S43) -> 0
A44: SUB TOTAL | B44: =SUM(B39:B43) -> 0 | C44: =SUM(C39:C43) -> 0 | D44: =SUM(D39:D43) -> 0 | E44: =SUM(E39:E43) -> 0 | F44: =SUM(F39:F43) -> 0 | G44: =SUM(G39:G43) -> 330 | I44: =SUM(I39:I43) -> 330 | K44: =SUM(K39:K43) -> 330 | M44: =SUM(M39:M43) -> 330 | O44: =SUM(O39:O43) -> 330 | Q44: =SUM(Q39:Q43) -> 330 | S44: =SUM(S39:S43) -> 330 | U44: =SUM(U39:U43) -> 2310
A45: SELF DEVELOPMEMT
A46: COURSE | H46: Not Paid | J46: Not Paid | L46: Not Paid | N46: Not Paid | R46: Not Paid | U46: =SUM(B46:S46) -> 0
A47: LESSONS | H47: Not Paid | J47: Not Paid | L47: Not Paid | N47: Not Paid | R47: Not Paid
A48: SUB TOTAL | B48: =SUM(B46) -> 0 | C48: =SUM(C46) -> 0 | D48: =SUM(D46) -> 0 | E48: =SUM(E46) -> 0 | F48: =SUM(F46) -> 0 | G48: =SUM(G46) -> 0 | I48: =SUM(I46) -> 0 | K48: =SUM(K46) -> 0 | M48: =SUM(M46) -> 0 | O48: =SUM(O46) -> 0 | Q48: =SUM(Q46) -> 0 | S48: =SUM(S46) -> 0 | U48: =SUM(U46:U47) -> 0
A49: LOAN DEBTS
A50: VANQUIS CARD | G50: 450 | H50: Paid | I50: 600 | J50: Not Paid | K50: 600 | L50: Not Paid | N50: Not Paid | O50: 5000 | P50: Not Paid | R50: Not Paid | U50: =SUM(B50:S50) -> 6650
A51: NATWEST CARD | G51: 300 | H51: Paid | I51: 300 | J51: Not Paid | K51: 300 | L51: Not Paid | N51: Not Paid | O51: 3000 | P51: Not Paid | R51: Not Paid | U51: =SUM(B51:S51) -> 3900
A52: AUDIO GEAR | G52: 175 | H52: Not Paid | I52: 175 | J52: Not Paid | K52: 175 | L52: Not Paid | M52: 175 | N52: Not Paid | O52: 175 | P52: Not Paid | R52: Not Paid | S52: 175 | U52: =SUM(B52:S52) -> 1050
A53: SUB TOTAL | B53: =SUM(B50:B52) -> 0 | C53: =SUM(C50:C52) -> 0 | D53: =SUM(D50:D52) -> 0 | E53: =SUM(E50:E52) -> 0 | F53: =SUM(F50:F52) -> 0 | G53: =SUM(G50:G52) -> 925 | I53: =SUM(I50:I52) -> 1075 | K53: =SUM(K50:K52) -> 1075 | M53: =SUM(M50:M52) -> 175 | O53: =SUM(O50:O52) -> 8175 | Q53: =SUM(Q50:Q52) -> 0 | S53: =SUM(S50:S52) -> 175 | U53: =SUM(B53:S53) -> 11600
A54: SELF CARE
A55: BARBERS | G55: 20 | H55: Paid | I55: 40 | J55: Not Paid | K55: 40 | L55: Not Paid | M55: 40 | N55: Not Paid | O55: 40 | P55: Not Paid | Q55: 60 | R55: Not Paid | S55: 60 | U55: =SUM(B55:S55) -> 300
A56: BODY CARE | G56: 0 | H56: Not Paid | J56: Not Paid | L56: Not Paid | N56: Not Paid | P56: Not Paid | R56: Not Paid | U56: =SUM(B56:S56) -> 0
A57: CLOTHES | G57: 0 | H57: Not Paid | J57: Not Paid | L57: Not Paid | N57: Not Paid | P57: Not Paid | R57: Not Paid | U57: =SUM(B57:S57) -> 0
A58: SUB TOTAL | B58: =SUM(B55:B57) -> 0 | C58: =SUM(C55:C57) -> 0 | D58: =SUM(D55:D57) -> 0 | E58: =SUM(E55:E57) -> 0 | F58: =SUM(F55:F57) -> 0 | G58: =SUM(G55:G57) -> 20 | I58: =SUM(I55:I57) -> 40 | K58: =SUM(K55:K57) -> 40 | M58: =SUM(M55:M57) -> 40 | O58: =SUM(O55:O57) -> 40 | Q58: =SUM(Q55:Q57) -> 60 | S58: =SUM(S55:S57) -> 60 | U58: =SUM(U55:U57) -> 300
A59: OTHER EXPENSIVE
A60: OTHER EXPENSIVE | G60: 180 | H60: Not Paid | J60: Not Paid | L60: Not Paid | N60: Not Paid | P60: Not Paid | R60: Not Paid | U60: =SUM(B60:S60) -> 180
A61: FLIGHT | G61: 276 | H61: Paid | J61: Not Paid | L61: Not Paid | N61: Not Paid | P61: Not Paid | R61: Not Paid | U61: =SUM(B61:S61) -> 276
A62: TRAIN TICKET | G62: 15 | H62: Not Paid
A63: HOTEL 1 | G63: 65 | H63: Paid | J63: Not Paid | L63: Not Paid | N63: Not Paid | P63: Not Paid | R63: Not Paid
A64: HOTEL 2 | G64: 150 | H64: Not Paid | J64: Not Paid | L64: Not Paid | N64: Not Paid | P64: Not Paid | R64: Not Paid | U64: =SUM(B64:S64) -> 150
A65: OWINGS | G65: 0 | H65: Not Paid | J65: Not Paid | L65: Not Paid | N65: Not Paid | P65: Not Paid | R65: Not Paid | U65: =SUM(B65:S65) -> 0
A66: GIFTS | G66: 0 | H66: Not Paid | J66: Not Paid | L66: Not Paid | N66: Not Paid | P66: Not Paid | R66: Not Paid | U66: =SUM(B66:S66) -> 0
A67: SUB TOTAL | B67: =SUM(B59:B66) -> 0 | C67: =SUM(C59:C66) -> 0 | D67: =SUM(D59:D66) -> 0 | E67: =SUM(E59:E66) -> 0 | F67: =SUM(F59:F66) -> 0 | G67: =SUM(G59:G66) -> 686 | I67: =SUM(I59:I66) -> 0 | K67: =SUM(K59:K66) -> 0 | M67: =SUM(M59:M66) -> 0 | O67: =SUM(O59:O66) -> 0 | Q67: =SUM(Q59:Q66) -> 0 | S67: =SUM(S59:S66) -> 0 | U67: =SUM(U59:U66) -> 606
A68: SAVINGS
A69: EMERGENCY FUNDS | G69: 0 | H69: Not Paid | J69: Not Paid | K69: 50 | L69: Not Paid | M69: 50 | N69: Not Paid | O69: 3000 | P69: Not Paid | Q69: 600 | R69: Not Paid | S69: 600 | U69: =SUM(B69:S69) -> 4300
A70: SINGLE SAVING | G70: 0 | H70: Not Paid | J70: Not Paid | L70: Not Paid | N70: Not Paid | P70: Not Paid | R70: Not Paid | U70: =SUM(B70:S70) -> 0
A71: HOME DEPOSIT | G71: 0 | H71: Not Paid | J71: Not Paid | L71: Not Paid | N71: Not Paid | O71: 400 | P71: Not Paid | Q71: 300 | R71: Not Paid | S71: 300 | U71: =SUM(B71:S71) -> 1000
A72: SUB TOTAL | B72: =SUM(B69:B71) -> 0 | C72: =SUM(C69:C71) -> 0 | D72: =SUM(D69:D71) -> 0 | E72: =SUM(E69:E71) -> 0 | F72: =SUM(F69:F71) -> 0 | G72: =SUM(G69:G71) -> 0 | I72: =SUM(I69:I71) -> 0 | K72: =SUM(K69:K71) -> 50 | M72: =SUM(M69:M71) -> 50 | O72: =SUM(O69:O71) -> 3400 | Q72: =SUM(Q69:Q71) -> 900 | S72: =SUM(S69:S71) -> 900 | U72: =SUM(U69:U71) -> 5300
A73: INVESTMENT CONTRIBUTION
A74: CYPTO | G74: 0 | H74: Not Paid | J74: Not Paid | L74: Not Paid | N74: Not Paid | R74: Not Paid
A75: TRADING 212 | H75: Not Paid | J75: Not Paid | L75: Not Paid | N75: Not Paid | O75: 50 | Q75: 50 | R75: Not Paid | S75: 50 | U75: =SUM(B75:S75) -> 150
A76: SUB TOTAL | B76: =SUM(B74:B75) -> 0 | C76: =SUM(C74:C75) -> 0 | D76: =SUM(D74:D75) -> 0 | E76: =SUM(E74:E75) -> 0 | F76: =SUM(F74:F75) -> 0 | G76: =SUM(G74:G75) -> 0 | I76: =SUM(I74:I75) -> 0 | K76: =SUM(K74:K75) -> 0 | M76: =SUM(M74:M75) -> 0 | O76: =SUM(O74:O75) -> 50 | Q76: =SUM(Q74:Q75) -> 50 | S76: =SUM(S74:S75) -> 50 | U76: =SUM(U74:U75) -> 150
A77: GRAND TOTAL | B77: =SUM(B8+B25+B37+B44+B53+B67+B76) -> 0 | C77: =SUM(C8+C18+C25+C37+C44++C48+C53+C58+C67+C72+C76) -> 0 | D77: =SUM(D8+D18+D25+D37+D44++D48+D53+D58+D67+D72+D76) -> 0 | E77: =SUM(E8+E18+E25+E37+E44++E48+E53+E58+E67+E72+E76) -> 0 | F77: =SUM(F8+F18+F25+F37+F44++F48+F53+F58+F67+F72+F76) -> 0 | G77: =SUM(G8+G18+G25+G37+G44++G48+G53+G58+G67+G72+G76) -> 4700 | I77: =SUM(I8+I18+I25+I37+I44++I48+I53+I58+I67+I72+I76) -> 4494 | K77: =SUM(K8+K18+K25+K37+K44++K48+K53+K58+K67+K72+K76) -> 4548 | M77: =SUM(M8+M18+M25+M37+M44++M48+M53+M58+M67+M72+M76) -> 3758 | O77: =SUM(O8+O18+O25+O37+O44++O48+O53+O67+O72+O76) -> 15037 | Q77: =SUM(Q8+Q18+Q25+Q37+Q44++Q48+Q53+Q67+Q72+Q76) -> 4362 | S77: =SUM(S8+S18+S25+S37+S44++S48+S53+S67+S72+S76) -> 4687 | U77: =SUM(B77:S77) -> 41586
A78: INCOME STREAM
A79: SALARY | G79: 4560 | I79: 4561 | K79: 4562 | M79: 4563 | O79: 15000 | Q79: 5000 | S79: 5000 | U79: =SUM(B79:S79) -> 43246
A80: PRODUCTION | U80: =SUM(B80:S80) -> 0
A81: MY EVENTS
A82: GIGS | G82: 150 | U82: =SUM(B82:S82) -> 150
A83: TAKE FORWARD | U83: =SUM(B83:S83) -> 0
A84: TOTAL INCOME | B84: =SUM(B79:B83) -> 0 | C84: =SUM(C79:C83) -> 0 | D84: =SUM(D79:D83) -> 0 | E84: =SUM(E79:E83) -> 0 | F84: =SUM(F79:F83) -> 0 | G84: =SUM(G79:G83) -> 4710 | I84: =SUM(I79:I83) -> 4561 | K84: =SUM(K79:K83) -> 4562 | M84: =SUM(M79:M83) -> 4563 | O84: =SUM(O79:O83) -> 15000 | Q84: =SUM(Q79:Q83) -> 5000 | S84: =SUM(S79:S83) -> 5000 | U84: =SUM(B84:S84) -> 43396
A85: AVAILABLE BUDGET | G85: =G84 - SUMIFS($G:$G, $H:$H, "Paid", $G:$G, ">0") -> 2299 | I85: =I84 - SUMIFS($I:$I, $J:$J, "Paid", $I:$I, ">0") -> 4561 | K85: =K84 - SUMIFS($K:$K, $L:$L, "Paid", $K:$K, ">0") -> 4562 | M85: =M84 - SUMIFS($M:$M, $N:$N, "Paid", $M:$M, ">0") -> 4563 | O85: =O84 - SUMIFS($O:$O, $P:$P, "Paid", $O:$O, ">0") -> 15000
A86: EXTRA SAVING | B86: =(B84-B77-'[1]House DECO & REPAIR 25'!$C$32) -> 0 | C86: =(C84-C77-'[1]House DECO & REPAIR 25'!$D$32) -> 0 | D86: =(D84-D77-'[1]House DECO & REPAIR 25'!$E$32) -> 0 | E86: =(E84-E77-'[1]House DECO & REPAIR 25'!$F$32) -> 0 | F86: =(F84-F77-'[1]House DECO & REPAIR 25'!$G$32) -> 0 | G86: =SUM(G84-G77) -> 10 | I86: =(I84-I77) -> 67 | K86: =(K84-K77) -> 14 | M86: =(M84-M77) -> 805 | O86: =(O84-O77) -> -37 | Q86: =(Q84-Q77) -> 638 | S86: =(S84-S77) -> 313 | U86: =SUM(B86:S86) -> 1810
Q87: YEAR END | U87: =SUM(U4:U86) -> 213280
Q89: TOTAL UNTOUCHED | U89: =SUM(U72+U76) -> 5450
Q90: SAVINGS | U90: =SUM(B86:S86) -> 1810

Sheet PERSONAL BUDGET 2026-2027
A1: 2026 - 2027 | B1: AUGUST | C1: SEPTEMBER | D1: OCTOBER | E1: NOVEMBER | F1: DECEMBER | G1: JANUARY | H1: FEBURARY | I1: MARCH | J1: APRIL | K1: MAY | L1: JUNE | M1: JULY | O1: YEAR TOTAL
A3: HOUSING COSTS
A4: RENT | B4: 1110 | C4: 1110 | D4: 1110 | E4: 1110 | F4: 1110 | G4: 1110 | H4: 1110 | I4: 1110 | J4: 1110 | K4: 1110 | L4: 1175 | M4: 1175 | O4: =SUM(B4:M4) -> 13450
A5: MORTGAGE | B5: 825 | C5: 825 | D5: 825 | E5: 825 | F5: 825 | G5: 825 | H5: 825 | I5: 825 | J5: 825 | K5: 825 | L5: 825 | M5: 825 | O5: =SUM(B5:M5) -> 9900
A6: COUNCIL TAX | B6: 170 | C6: 170 | D6: 170 | E6: 170 | F6: 170 | G6: 170 | H6: 170 | I6: 170 | J6: 170 | K6: 170 | L6: 170 | M6: 170 | O6: =SUM(B6:M6) -> 2040
A7: SUB TOTAL | B7: =SUM(B4:B6) -> 2105 | C7: =SUM(C4:C6) -> 2105 | D7: =SUM(D4:D6) -> 2105 | E7: =SUM(E4:E6) -> 2105 | F7: =SUM(F4:F6) -> 2105 | G7: =SUM(G4:G6) -> 2105 | H7: =SUM(H4:H6) -> 2105 | I7: =SUM(I4:I6) -> 2105 | ... M7: =SUM(M4:M6) -> 2170 | O7: =SUM(O4:O6) -> 25390
A8: UTILITIES
A9: EE | B9: 55 | C9: 55 | D9: 55 | E9: 55 | F9: 55 | G9: 55 | H9: 35 | I9: 35 | J9: 35 | K9: 35 | L9: 35 | M9: 35 | O9: =SUM(B9:M9) -> 540
A10: SKY | B10: 135 | C10: 135 | D10: 135 | E10: 135 | F10: 135 | G10: 135 | H10: 135 | I10: 135 | J10: 135 | K10: 160 | L10: 160 | M10: 160 | O10: =SUM(B10:M10) -> 1695
A11: ECLECTRICITY | B11: 70 | C11: 70 | D11: 70 | E11: 70 | F11: 70 | G11: 70 | H11: 70 | I11: 70 | J11: 70 | K11: 70 | L11: 70 | M11: 70 | O11: =SUM(B11:M11) -> 840
A12: THAMES WATER | B12: 40 | C12: 40 | D12: 40 | E12: 40 | F12: 40 | G12: 40 | H12: 40 | I12: 40 | J12: 40 | K12: 40 | L12: 40 | M12: 40 | O12: =SUM(B12:M12) -> 480
A13: ZURICH | B13: 15 | C13: 15 | D13: 15 | E13: 15 | F13: 15 | G13: 15 | H13: 15 | I13: 15 | J13: 15 | K13: 15 | L13: 15 | M13: 15 | O13: =SUM(B13:M13) -> 180
A14: GAS | B14: 30 | C14: 30 | D14: 30 | E14: 30 | F14: 30 | G14: 30 | H14: 30 | I14: 30 | J14: 30 | K14: 30 | L14: 30 | M14: 30 | O14: =SUM(B14:M14) -> 360
A15: APPLICANE INSURANCE | B15: 25 | C15: 25 | D15: 25 | E15: 25 | F15: 25 | G15: 25 | H15: 25 | I15: 25 | J15: 25 | K15: 25 | L15: 25 | M15: 25 | O15: =SUM(B15:M15) -> 300
A16: LIFE INSURANCE | B16: 15 | C16: 15 | D16: 15 | E16: 15 | F16: 15 | G16: 15 | H16: 15 | I16: 15 | J16: 15 | K16: 15 | L16: 15 | M16: 15 | O16: =SUM(B16:M16) -> 180
A17: SUB TOTAL | B17: =SUM(B9:B16) -> 385 | C17: =SUM(C9:C16) -> 385 | D17: =SUM(D9:D16) -> 385 | E17: =SUM(E9:E16) -> 385 | F17: =SUM(F9:F16) -> 385 | G17: =SUM(G9:G16) -> 385 | H17: =SUM(H9:H16) -> 365 | I17: =SUM(I9:I16) -> 365 | ... M17: =SUM(M9:M16) -> 390 | O17: =SUM(O9:O16) -> 4575
A18: ALLOWANCES
A19: WORK TRAVEL | B19: 60 | C19: 60 | D19: 60 | E19: 60 | F19: 60 | G19: 60 | H19: 60 | I19: 60 | J19: 60 | K19: 60 | L19: 60 | M19: 60 | O19: =SUM(B19:M19) -> 720
A20: UBER | B20: 20 | C20: 20 | D20: 20 | E20: 20 | F20: 20 | G20: 20 | H20: 20 | I20: 20 | J20: 20 | K20: 20 | L20: 20 | M20: 20 | O20: 20
A21: FOOD | B21: 200 | C21: 200 | D21: 200 | E21: 200 | F21: 200 | G21: 200 | H21: 200 | I21: 200 | J21: 200 | K21: 300 | L21: 300 | M21: 300 | O21: =SUM(B21:M21) -> 2700
A22: LUNCH | B22: 70 | C22: 70 | D22: 70 | E22: 70 | F22: 70 | G22: 70 | H22: 70 | I22: 70 | J22: 70 | K22: 70 | L22: 70 | M22: 70 | O22: =SUM(B22:M22) -> 840
A23: MONTHLY ALLOWANCE | B23: 250 | C23: 150 | D23: 100 | E23: 150 | F23: 280 | G23: 150 | H23: 150 | I23: 150 | J23: 280 | K23: 100 | L23: 100 | M23: 100 | O23: =SUM(B23:M23) -> 1960
A24: SUB TOTAL | B24: =SUM(B19:B23) -> 600 | C24: =SUM(C19:C23) -> 500 | D24: =SUM(D19:D23) -> 450 | E24: =SUM(E19:E23) -> 500 | F24: =SUM(F19:F23) -> 630 | G24: =SUM(G19:G23) -> 500 | H24: =SUM(H19:H23) -> 500 | I24: =SUM(I19:I23) -> 500 | ... M24: =SUM(M19:M23) -> 550 | O24: =SUM(O19:O23) -> 6240
A25: SUBSCRIPTIONS
A26: GYM | O26: =SUM(B26:M26) -> 0
A27: SERATO | B27: 10 | C27: 10 | D27: 10 | E27: 10 | F27: 10 | G27: 10 | H27: 10 | I27: 10 | J27: 10 | K27: 10 | L27: 10 | M27: 10 | O27: =SUM(B27:M27) -> 120
A28: SPLICE | B28: 10 | C28: 10 | D28: 10 | E28: 10 | F28: 10 | G28: 10 | H28: 10 | I28: 10 | J28: 10 | K28: 10 | L28: 10 | M28: 10 | O28: =SUM(B28:M28) -> 120
A29: SITE GROUND | B29: 50 | C29: 50 | D29: 50 | E29: 50 | F29: 50 | G29: 50 | H29: 50 | I29: 50 | J29: 50 | K29: 50 | L29: 50 | M29: 50 | O29: =SUM(B29:M29) -> 600
A30: DISNEY PLUS | B30: 5 | C30: 5 | D30: 5 | E30: 5 | F30: 5 | G30: 5 | H30: 5 | I30: 5 | J30: 5 | K30: 5 | L30: 5 | M30: 5 | O30: =SUM(B30:M30) -> 60
A31: NETFLIX | B31: 15 | C31: 15 | D31: 15 | E31: 15 | F31: 15 | G31: 15 | H31: 15 | I31: 15 | J31: 15 | K31: 15 | L31: 15 | M31: 15 | O31: =SUM(B31:M31) -> 180
A32: SPOTIFY | B32: 20 | C32: 20 | D32: 20 | E32: 20 | F32: 20 | G32: 20 | H32: 20 | I32: 20 | J32: 20 | K32: 20 | L32: 20 | M32: 20 | O32: =SUM(B32:M32) -> 240
A33: MICROSOFT | B33: 8 | C33: 8 | D33: 8 | E33: 8 | F33: 8 | G33: 8 | H33: 8 | I33: 8 | J33: 8 | K33: 6 | L33: 6 | M33: 6 | O33: =SUM(B33:M33) -> 90
A34: APPLE ITUNES | B34: 12 | C34: 12 | D34: 12 | E34: 12 | F34: 12 | G34: 12 | H34: 12 | I34: 12 | J34: 12 | K34: 12 | L34: 12 | M34: 12 | O34: =SUM(B34:M34) -> 144
A35: REVOLUT | B35: 8 | C35: 8 | D35: 8 | E35: 8 | F35: 8 | G35: 8 | H35: 8 | I35: 8 | J35: 8 | K35: 8 | L35: 8 | M35: 8 | O35: =SUM(B35:M35) -> 96
A36: SUB TOTAL | B36: =SUM(B26:B35) -> 138 | C36: =SUM(C26:C35) -> 138 | D36: =SUM(D26:D35) -> 138 | E36: =SUM(E26:E35) -> 138 | F36: =SUM(F26:F35) -> 138 | G36: =SUM(G26:G35) -> 138 | H36: =SUM(H26:H35) -> 138 | I36: =SUM(I26:I35) -> 138 | ... M36: =SUM(M26:M35) -> 136 | O36: =SUM(O26:O35) -> 1650
A37: CHILDCARE
A38: JAYDA | B38: 180 | C38: 180 | D38: 180 | E38: 180 | F38: 180 | G38: 180 | H38: 180 | I38: 180 | J38: 180 | K38: 180 | L38: 180 | M38: 180 | O38: =SUM(B38:M38) -> 2160
A39: JAYDA ALLOWANCE | B39: 100 | C39: 100 | D39: 100 | E39: 100 | F39: 100 | G39: 100 | H39: 100 | I39: 100 | J39: 100 | K39: 100 | L39: 100 | M39: 100 | O39: =SUM(B39:M39) -> 1200
A40: JAYDA SAVING 2 | B40: 50 | C40: 50 | D40: 50 | E40: 50 | F40: 50 | G40: 50 | H40: 50 | I40: 50 | J40: 50 | K40: 50 | L40: 50 | M40: 50 | O40: =SUM(B40:M40) -> 600
A41: JAYDA DANCE | O41: =SUM(B41:M41) -> 0
A42: JAYDA HOLIDAY | O42: =SUM(B42:M42) -> 0
A43: JAYDA SCHOOL | O43: =SUM(B43:M43) -> 0
A44: SUB TOTAL | B44: =SUM(B38:B43) -> 330 | C44: =SUM(C38:C43) -> 330 | D44: =SUM(D38:D43) -> 330 | E44: =SUM(E38:E43) -> 330 | F44: =SUM(F38:F43) -> 330 | G44: =SUM(G38:G43) -> 330 | H44: =SUM(H38:H43) -> 330 | I44: =SUM(I38:I43) -> 330 | ... M44: =SUM(M38:M43) -> 330 | O44: =SUM(O38:O43) -> 3960
A45: SELF DEVELOPMEMT
A46: COURSE | O46: =SUM(B46:M46) -> 0
A48: SUB TOTAL | B48: =SUM(B46) -> 0 | C48: =SUM(C46) -> 0 | D48: =SUM(D46) -> 0 | E48: =SUM(E46) -> 0 | F48: =SUM(F46) -> 0 | G48: =SUM(G46) -> 0 | H48: =SUM(H46) -> 0 | I48: =SUM(I46) -> 0 | ... M48: =SUM(M46) -> 0 | O48: =SUM(O46:O47) -> 0
A49: LOAN DEBTS
A50: CARD | O50: =SUM(B50:M50) -> 0
A51: AUDIO GEAR | B51: 175 | C51: 175 | D51: 175 | E51: 175 | F51: 175 | G51: 175 | H51: 175 | I51: 175 | J51: 175 | K51: 175 | O51: =SUM(B51:M51) -> 1750
A52: SUB TOTAL | B52: =SUM(B50:B51) -> 175 | C52: =SUM(C50:C51) -> 175 | D52: =SUM(D50:D51) -> 175 | E52: =SUM(E50:E51) -> 175 | F52: =SUM(F50:F51) -> 175 | G52: =SUM(G50:G51) -> 175 | H52: =SUM(H50:H51) -> 175 | I52: =SUM(I50:I51) -> 175 | ... M52: =SUM(M50:M51) -> 0 | O52: =SUM(B52:M52) -> 1750
A53: SELF CARE
A54: BARBERS | B54: 40 | C54: 40 | D54: 60 | E54: 60 | F54: 60 | G54: 60 | H54: 60 | I54: 60 | J54: 60 | K54: 60 | L54: 60 | M54: 60 | O54: =SUM(B54:M54) -> 680
A55: BODY CARE | K55: 100 | O55: =SUM(B55:M55) -> 100
A56: CLOTHES | O56: =SUM(B56:M56) -> 0
A57: SUB TOTAL | B57: =SUM(B54:B56) -> 40 | C57: =SUM(C54:C56) -> 40 | D57: =SUM(D54:D56) -> 60 | E57: =SUM(E54:E56) -> 60 | F57: =SUM(F54:F56) -> 60 | G57: =SUM(G54:G56) -> 60 | H57: =SUM(H54:H56) -> 60 | I57: =SUM(I54:I56) -> 60 | ... M57: =SUM(M54:M56) -> 60 | O57: =SUM(O54:O56) -> 780
A58: OTHER EXPENSIVE
A59: OTHER | O59: =SUM(B59:M59) -> 0
A60: GIFTS | O60: =SUM(B60:M60) -> 0
A61: SUB TOTAL | B61: =SUM(B58:B60) -> 0 | C61: =SUM(C58:C60) -> 0 | D61: =SUM(D58:D60) -> 0 | E61: =SUM(E58:E60) -> 0 | F61: =SUM(F58:F60) -> 0 | G61: =SUM(G58:G60) -> 0 | H61: =SUM(H58:H60) -> 0 | I61: =SUM(I58:I60) -> 0 | ... M61: =SUM(M58:M60) -> 0 | O61: =SUM(O58:O60) -> 0
A62: SAVINGS
A63: EMERGENCY FUNDS | B63: 300 | C63: 300 | D63: 300 | E63: 300 | F63: 300 | G63: 300 | H63: 300 | I63: 300 | J63: 300 | K63: 8000 | L63: 600 | M63: 600 | O63: =SUM(B63:M63) -> 11900
A64: SINGLE SAVING | C64: 100 | D64: 100 | E64: 100 | F64: 100 | G64: 100 | H64: 100 | I64: 100 | J64: 100 | K64: 500 | L64: 100 | M64: 100 | O64: =SUM(B64:M64) -> 1500
A65: HOME DEPOSIT | B65: 700 | C65: 700 | D65: 700 | E65: 700 | F65: 700 | G65: 700 | H65: 700 | I65: 700 | J65: 700 | K65: 300 | L65: 300 | M65: 300 | O65: =SUM(B65:M65) -> 7200
A66: SUB TOTAL | B66: =SUM(B63:B65) -> 1000 | C66: =SUM(C63:C65) -> 1100 | D66: =SUM(D63:D65) -> 1100 | E66: =SUM(E63:E65) -> 1100 | F66: =SUM(F63:F65) -> 1100 | G66: =SUM(G63:G65) -> 1100 | H66: =SUM(H63:H65) -> 1100 | I66: =SUM(I63:I65) -> 1100 | ... M66: =SUM(M63:M65) -> 1000 | O66: =SUM(O63:O65) -> 20600
A67: INVESTMENT CONTRIBUTION
A69: TRADING 212 | B69: 50 | C69: 50 | D69: 50 | E69: 50 | F69: 50 | G69: 50 | H69: 50 | I69: 50 | J69: 50 | K69: 50 | L69: 50 | M69: 50 | O69: =SUM(B69:M69) -> 600
A70: SUB TOTAL | B70: =SUM(B68:B69) -> 50 | C70: =SUM(C68:C69) -> 50 | D70: =SUM(D68:D69) -> 50 | E70: =SUM(E68:E69) -> 50 | F70: =SUM(F68:F69) -> 50 | G70: =SUM(G68:G69) -> 50 | H70: =SUM(H68:H69) -> 50 | I70: =SUM(I68:I69) -> 50 | ... M70: =SUM(M68:M69) -> 50 | O70: =SUM(O68:O69) -> 600
A71: GRAND TOTAL | B71: =SUM(B7+B17+B24+B36+B44+B48+B52+B57+B61+B66+B70) -> 4823 | C71: =SUM(C7+C17+C24+C36+C44+C48+C52+C57+C61+C66+C70) -> 4823 | D71: =SUM(D7+D17+D24+D36+D44+D48+D52+D57+D61+D66+D70) -> 4793 | E71: =SUM(E7+E17+E24+E36+E44+E48+E52+E57+E61+E66+E70) -> 4843 | F71: =SUM(F7+F17+F24+F36+F44+F48+F52+F57+F61+F66+F70) -> 4973 | G71: =SUM(G7+G17+G24+G36+G44+G48+G52+G57+G61+G66+G70) -> 4843 | H71: =SUM(H7+H17+H24+H36+H44+H48+H52+H57+H61+H66+H70) -> 4823 | I71: =SUM(I7+I17+I24+I36+I44+I48+I52+I57+I61+I66+I70) -> 4823 | J71: =SUM(J7+J17+J24+J36+J44++J48+J52+J61+J66+J70) -> 4893 | K71: =SUM(K7+K17+K24+K36+K44++K48+K52+K61+K66+K70) -> 12536 | L71: =SUM(L7+L17+L24+L36+L44++L48+L52+L61+L66+L70) -> 4626 | M71: =SUM(M7+M17+M24+M36+M44++M48+M52+M61+M66+M70) -> 4626 | O71: =SUM(B71:M71) -> 65425
A72: INCOME STREAM
A73: SALARY | B73: 5040 | C73: 5040 | D73: 5040 | E73: 5040 | F73: 5040 | G73: 5040 | H73: 5040 | I73: 4850 | J73: 4850 | K73: 14500 | L73: 5000 | M73: 5000 | O73: =SUM(B73:M73) -> 69480
A74: PRODUCTION | O74: =SUM(B74:M74) -> 0
A75: MY EVENTS | O75: =SUM(B75:M75) -> 0
A76: GIGS | B76: 800 | O76: =SUM(B76:M76) -> 800
A77: TOTAL INCOME | B77: =SUM(B73:B76) -> 5840 | C77: =SUM(C73:C76) -> 5040 | D77: =SUM(D73:D76) -> 5040 | E77: =SUM(E73:E76) -> 5040 | F77: =SUM(F73:F76) -> 5040 | G77: =SUM(G73:G76) -> 5040 | H77: =SUM(H73:H76) -> 5040 | I77: =SUM(I73:I76) -> 4850 | ... M77: =SUM(M73:M76) -> 5000 | O77: =SUM(B77:M77) -> 70280
A78: REMAINING
A80: EXTRA SAVING | B80: =(B77-B71-'[1]House DECO & REPAIR 25'!$C$32) -> 1017 | C80: =(C77-C71-'[1]House DECO & REPAIR 25'!$D$32) -> 217 | D80: =(D77-D71-'[1]House DECO & REPAIR 25'!$E$32) -> 247 | E80: =(E77-E71-'[1]House DECO & REPAIR 25'!$F$32) -> 197 | F80: =(F77-F71-'[1]House DECO & REPAIR 25'!$G$32) -> 67 | G80: =(G77-G71) -> 197 | H80: =(H77-H71) -> 217 | I80: =(I77-I71) -> 27 | J80: =(J77-J71) -> -43 | K80: =(K77-K71) -> 1964 | L80: =(L77-L71) -> 374 | M80: =(M77-M71) -> 374 | O80: =SUM(B80:M80) -> 4855
L81: YEAR END | O81: =SUM(O4:O80) -> 341930
L83: TOTAL UNTOUCHED | O83: =SUM(O66+O70) -> 21200
L84: SAVINGS | O84: =SUM(B80:M80) -> 4855

Sheet PERSONAL BUDGET 2027-2028
A1: 2027 - 2028 | B1: AUGUST | C1: SEPTEMBER | D1: OCTOBER | E1: NOVEMBER | F1: DECEMBER | G1: JANUARY | H1: FEBURARY | I1: MARCH | J1: APRIL | K1: MAY | L1: JUNE | M1: JULY | O1: YEAR TOTAL
A3: HOUSING COSTS
A4: RENT | B4: 1175 | C4: 1175 | D4: 1175 | E4: 1175 | F4: 1175 | G4: 1175 | H4: 1175 | I4: 1175 | J4: 1175 | K4: 1175 | L4: 1200 | M4: 1200 | O4: =SUM(B4:M4) -> 14150
A5: MORTGAGE | B5: 825 | C5: 825 | D5: 825 | E5: 825 | F5: 825 | G5: 825 | H5: 825 | I5: 825 | J5: 825 | K5: 825 | L5: 825 | M5: 825 | O5: =SUM(B5:M5) -> 9900
A6: COUNCIL TAX | B6: 170 | C6: 170 | D6: 170 | E6: 170 | F6: 170 | G6: 170 | H6: 170 | I6: 170 | J6: 170 | K6: 170 | L6: 170 | M6: 170 | O6: =SUM(B6:M6) -> 2040
A7: SUB TOTAL | B7: =SUM(B4:B6) -> 2170 | C7: =SUM(C4:C6) -> 2170 | D7: =SUM(D4:D6) -> 2170 | E7: =SUM(E4:E6) -> 2170 | F7: =SUM(F4:F6) -> 2170 | G7: =SUM(G4:G6) -> 2170 | H7: =SUM(H4:H6) -> 2170 | I7: =SUM(I4:I6) -> 2170 | ... M7: =SUM(M4:M6) -> 2195 | O7: =SUM(O4:O6) -> 26090
A8: UTILITIES
A9: EE | B9: 55 | C9: 55 | D9: 55 | E9: 55 | F9: 55 | G9: 55 | H9: 35 | I9: 35 | J9: 35 | K9: 35 | L9: 35 | M9: 35 | O9: =SUM(B9:M9) -> 540
A10: SKY | B10: 135 | C10: 135 | D10: 135 | E10: 135 | F10: 135 | G10: 135 | H10: 135 | I10: 135 | J10: 135 | K10: 160 | L10: 160 | M10: 160 | O10: =SUM(B10:M10) -> 1695
A11: ECLECTRICITY | B11: 70 | C11: 70 | D11: 70 | E11: 70 | F11: 70 | G11: 70 | H11: 70 | I11: 70 | J11: 70 | K11: 70 | L11: 70 | M11: 70 | O11: =SUM(B11:M11) -> 840
A12: THAMES WATER | B12: 40 | C12: 40 | D12: 40 | E12: 40 | F12: 40 | G12: 40 | H12: 40 | I12: 40 | J12: 40 | K12: 40 | L12: 40 | M12: 40 | O12: =SUM(B12:M12) -> 480
A13: ZURICH | B13: 15 | C13: 15 | D13: 15 | E13: 15 | F13: 15 | G13: 15 | H13: 15 | I13: 15 | J13: 15 | K13: 15 | L13: 15 | M13: 15 | O13: =SUM(B13:M13) -> 180
A14: GAS | B14: 30 | C14: 30 | D14: 30 | E14: 30 | F14: 30 | G14: 30 | H14: 30 | I14: 30 | J14: 30 | K14: 30 | L14: 30 | M14: 30 | O14: =SUM(B14:M14) -> 360
A15: APPLICANE INSURANCE | B15: 25 | C15: 25 | D15: 25 | E15: 25 | F15: 25 | G15: 25 | H15: 25 | I15: 25 | J15: 25 | K15: 25 | L15: 25 | M15: 25 | O15: =SUM(B15:M15) -> 300
A16: LIFE INSURANCE | B16: 15 | C16: 15 | D16: 15 | E16: 15 | F16: 15 | G16: 15 | H16: 15 | I16: 15 | J16: 15 | K16: 15 | L16: 15 | M16: 15 | O16: =SUM(B16:M16) -> 180
A17: SUB TOTAL | B17: =SUM(B9:B16) -> 385 | C17: =SUM(C9:C16) -> 385 | D17: =SUM(D9:D16) -> 385 | E17: =SUM(E9:E16) -> 385 | F17: =SUM(F9:F16) -> 385 | G17: =SUM(G9:G16) -> 385 | H17: =SUM(H9:H16) -> 365 | I17: =SUM(I9:I16) -> 365 | ... M17: =SUM(M9:M16) -> 390 | O17: =SUM(O9:O16) -> 4575
A18: ALLOWANCES
A19: WORK TRAVEL | B19: 60 | C19: 60 | D19: 60 | E19: 60 | F19: 60 | G19: 60 | H19: 60 | I19: 60 | J19: 60 | K19: 60 | L19: 60 | M19: 60 | O19: =SUM(B19:M19) -> 720
A20: UBER | B20: 20 | C20: 20 | D20: 20 | E20: 20 | F20: 20 | G20: 20 | H20: 20 | I20: 20 | J20: 20 | K20: 20 | L20: 20 | M20: 20 | O20: 20
A21: FOOD | B21: 200 | C21: 200 | D21: 200 | E21: 200 | F21: 200 | G21: 200 | H21: 200 | I21: 200 | J21: 200 | K21: 300 | L21: 300 | M21: 300 | O21: =SUM(B21:M21) -> 2700
A22: LUNCH | B22: 70 | C22: 70 | D22: 70 | E22: 70 | F22: 70 | G22: 70 | H22: 70 | I22: 70 | J22: 70 | K22: 70 | L22: 70 | M22: 70 | O22: =SUM(B22:M22) -> 840
A23: MONTHLY ALLOWANCE | B23: 250 | C23: 150 | D23: 100 | E23: 150 | F23: 280 | G23: 150 | H23: 150 | I23: 150 | J23: 280 | K23: 100 | L23: 100 | M23: 100 | O23: =SUM(B23:M23) -> 1960
A24: SUB TOTAL | B24: =SUM(B19:B23) -> 600 | C24: =SUM(C19:C23) -> 500 | D24: =SUM(D19:D23) -> 450 | E24: =SUM(E19:E23) -> 500 | F24: =SUM(F19:F23) -> 630 | G24: =SUM(G19:G23) -> 500 | H24: =SUM(H19:H23) -> 500 | I24: =SUM(I19:I23) -> 500 | ... M24: =SUM(M19:M23) -> 550 | O24: =SUM(O19:O23) -> 6240
A25: SUBSCRIPTIONS
A26: GYM | O26: =SUM(B26:M26) -> 0
A27: SERATO | B27: 10 | C27: 10 | D27: 10 | E27: 10 | F27: 10 | G27: 10 | H27: 10 | I27: 10 | J27: 10 | K27: 10 | L27: 10 | M27: 10 | O27: =SUM(B27:M27) -> 120
A28: SPLICE | B28: 10 | C28: 10 | D28: 10 | E28: 10 | F28: 10 | G28: 10 | H28: 10 | I28: 10 | J28: 10 | K28: 10 | L28: 10 | M28: 10 | O28: =SUM(B28:M28) -> 120
A29: SITE GROUND | B29: 50 | C29: 50 | D29: 50 | E29: 50 | F29: 50 | G29: 50 | H29: 50 | I29: 50 | J29: 50 | K29: 50 | L29: 50 | M29: 50 | O29: =SUM(B29:M29) -> 600
A30: DISNEY PLUS | B30: 5 | C30: 5 | D30: 5 | E30: 5 | F30: 5 | G30: 5 | H30: 5 | I30: 5 | J30: 5 | K30: 5 | L30: 5 | M30: 5 | O30: =SUM(B30:M30) -> 60
A31: NETFLIX | B31: 15 | C31: 15 | D31: 15 | E31: 15 | F31: 15 | G31: 15 | H31: 15 | I31: 15 | J31: 15 | K31: 15 | L31: 15 | M31: 15 | O31: =SUM(B31:M31) -> 180
A32: SPOTIFY | B32: 20 | C32: 20 | D32: 20 | E32: 20 | F32: 20 | G32: 20 | H32: 20 | I32: 20 | J32: 20 | K32: 20 | L32: 20 | M32: 20 | O32: =SUM(B32:M32) -> 240
A33: MICROSOFT | B33: 8 | C33: 8 | D33: 8 | E33: 8 | F33: 8 | G33: 8 | H33: 8 | I33: 8 | J33: 8 | K33: 6 | L33: 6 | M33: 6 | O33: =SUM(B33:M33) -> 90
A34: APPLE ITUNES | B34: 12 | C34: 12 | D34: 12 | E34: 12 | F34: 12 | G34: 12 | H34: 12 | I34: 12 | J34: 12 | K34: 12 | L34: 12 | M34: 12 | O34: =SUM(B34:M34) -> 144
A35: REVOLUT | B35: 8 | C35: 8 | D35: 8 | E35: 8 | F35: 8 | G35: 8 | H35: 8 | I35: 8 | J35: 8 | K35: 8 | L35: 8 | M35: 8 | O35: =SUM(B35:M35) -> 96
A36: SUB TOTAL | B36: =SUM(B26:B35) -> 138 | C36: =SUM(C26:C35) -> 138 | D36: =SUM(D26:D35) -> 138 | E36: =SUM(E26:E35) -> 138 | F36: =SUM(F26:F35) -> 138 | G36: =SUM(G26:G35) -> 138 | H36: =SUM(H26:H35) -> 138 | I36: =SUM(I26:I35) -> 138 | ... M36: =SUM(M26:M35) -> 136 | O36: =SUM(O26:O35) -> 1650
A37: CHILDCARE
A38: JAYDA | B38: 180 | C38: 180 | D38: 180 | E38: 180 | F38: 180 | G38: 180 | H38: 180 | I38: 180 | J38: 180 | K38: 180 | L38: 180 | M38: 180 | O38: =SUM(B38:M38) -> 2160
A39: JAYDA ALLOWANCE | B39: 100 | C39: 100 | D39: 100 | E39: 100 | F39: 100 | G39: 100 | H39: 100 | I39: 100 | J39: 100 | K39: 100 | L39: 100 | M39: 100 | O39: =SUM(B39:M39) -> 1200
A40: JAYDA SAVING 2 | B40: 50 | C40: 50 | D40: 50 | E40: 50 | F40: 50 | G40: 50 | H40: 50 | I40: 50 | J40: 50 | K40: 50 | L40: 50 | M40: 50 | O40: =SUM(B40:M40) -> 600
A41: JAYDA DANCE | O41: =SUM(B41:M41) -> 0
A42: JAYDA HOLIDAY | O42: =SUM(B42:M42) -> 0
A43: JAYDA SCHOOL | O43: =SUM(B43:M43) -> 0
A44: SUB TOTAL | B44: =SUM(B38:B43) -> 330 | C44: =SUM(C38:C43) -> 330 | D44: =SUM(D38:D43) -> 330 | E44: =SUM(E38:E43) -> 330 | F44: =SUM(F38:F43) -> 330 | G44: =SUM(G38:G43) -> 330 | H44: =SUM(H38:H43) -> 330 | I44: =SUM(I38:I43) -> 330 | ... M44: =SUM(M38:M43) -> 330 | O44: =SUM(O38:O43) -> 3960
A45: SELF DEVELOPMEMT
A46: COURSE | O46: =SUM(B46:M46) -> 0
A48: SUB TOTAL | B48: =SUM(B46) -> 0 | C48: =SUM(C46) -> 0 | D48: =SUM(D46) -> 0 | E48: =SUM(E46) -> 0 | F48: =SUM(F46) -> 0 | G48: =SUM(G46) -> 0 | H48: =SUM(H46) -> 0 | I48: =SUM(I46) -> 0 | ... M48: =SUM(M46) -> 0 | O48: =SUM(O46:O47) -> 0
A49: LOAN DEBTS
A50: CARD | O50: =SUM(B50:M50) -> 0
A51: AUDIO GEAR | O51: =SUM(B51:M51) -> 0
A52: SUB TOTAL | B52: =SUM(B50:B51) -> 0 | C52: =SUM(C50:C51) -> 0 | D52: =SUM(D50:D51) -> 0 | E52: =SUM(E50:E51) -> 0 | F52: =SUM(F50:F51) -> 0 | G52: =SUM(G50:G51) -> 0 | H52: =SUM(H50:H51) -> 0 | I52: =SUM(I50:I51) -> 0 | ... M52: =SUM(M50:M51) -> 0 | O52: =SUM(B52:M52) -> 0
A53: SELF CARE
A54: BARBERS | B54: 40 | C54: 40 | D54: 60 | E54: 60 | F54: 60 | G54: 60 | H54: 60 | I54: 60 | J54: 60 | K54: 60 | L54: 60 | M54: 60 | O54: =SUM(B54:M54) -> 680
A55: BODY CARE | K55: 100 | O55: =SUM(B55:M55) -> 100
A56: CLOTHES | O56: =SUM(B56:M56) -> 0
A57: SUB TOTAL | B57: =SUM(B54:B56) -> 40 | C57: =SUM(C54:C56) -> 40 | D57: =SUM(D54:D56) -> 60 | E57: =SUM(E54:E56) -> 60 | F57: =SUM(F54:F56) -> 60 | G57: =SUM(G54:G56) -> 60 | H57: =SUM(H54:H56) -> 60 | I57: =SUM(I54:I56) -> 60 | ... M57: =SUM(M54:M56) -> 60 | O57: =SUM(O54:O56) -> 780
A58: OTHER EXPENSIVE
A59: OTHER | O59: =SUM(B59:M59) -> 0
A60: GIFTS | O60: =SUM(B60:M60) -> 0
A61: SUB TOTAL | B61: =SUM(B58:B60) -> 0 | C61: =SUM(C58:C60) -> 0 | D61: =SUM(D58:D60) -> 0 | E61: =SUM(E58:E60) -> 0 | F61: =SUM(F58:F60) -> 0 | G61: =SUM(G58:G60) -> 0 | H61: =SUM(H58:H60) -> 0 | I61: =SUM(I58:I60) -> 0 | ... M61: =SUM(M58:M60) -> 0 | O61: =SUM(O58:O60) -> 0
A62: SAVINGS
A63: EMERGENCY FUNDS | B63: 300 | C63: 300 | D63: 300 | E63: 300 | F63: 300 | G63: 300 | H63: 300 | I63: 300 | J63: 300 | K63: 8000 | L63: 600 | M63: 600 | O63: =SUM(B63:M63) -> 11900
A64: SINGLE SAVING | C64: 100 | D64: 100 | E64: 100 | F64: 100 | G64: 100 | H64: 100 | I64: 100 | J64: 100 | K64: 500 | L64: 100 | M64: 100 | O64: =SUM(B64:M64) -> 1500
A65: HOME DEPOSIT | B65: 700 | C65: 700 | D65: 700 | E65: 700 | F65: 2000 | G65: 700 | H65: 700 | I65: 700 | J65: 700 | K65: 300 | L65: 300 | M65: 300 | O65: =SUM(B65:M65) -> 8500
A66: SUB TOTAL | B66: =SUM(B63:B65) -> 1000 | C66: =SUM(C63:C65) -> 1100 | D66: =SUM(D63:D65) -> 1100 | E66: =SUM(E63:E65) -> 1100 | F66: =SUM(F63:F65) -> 2400 | G66: =SUM(G63:G65) -> 1100 | H66: =SUM(H63:H65) -> 1100 | I66: =SUM(I63:I65) -> 1100 | ... M66: =SUM(M63:M65) -> 1000 | O66: =SUM(O63:O65) -> 21900
A67: INVESTMENT CONTRIBUTION
A69: TRADING 212 | B69: 50 | C69: 50 | D69: 50 | E69: 50 | F69: 50 | G69: 50 | H69: 50 | I69: 50 | J69: 50 | K69: 50 | L69: 50 | M69: 50 | O69: =SUM(B69:M69) -> 600
A70: SUB TOTAL | B70: =SUM(B68:B69) -> 50 | C70: =SUM(C68:C69) -> 50 | D70: =SUM(D68:D69) -> 50 | E70: =SUM(E68:E69) -> 50 | F70: =SUM(F68:F69) -> 50 | G70: =SUM(G68:G69) -> 50 | H70: =SUM(H68:H69) -> 50 | I70: =SUM(I68:I69) -> 50 | ... M70: =SUM(M68:M69) -> 50 | O70: =SUM(O68:O69) -> 600
A71: GRAND TOTAL | B71: =SUM(B7+B17+B24+B36+B44+B48+B52+B57+B61+B66+B70) -> 4713 | C71: =SUM(C7+C17+C24+C36+C44+C48+C52+C57+C61+C66+C70) -> 4713 | D71: =SUM(D7+D17+D24+D36+D44+D48+D52+D57+D61+D66+D70) -> 4683 | E71: =SUM(E7+E17+E24+E36+E44+E48+E52+E57+E61+E66+E70) -> 4733 | F71: =SUM(F7+F17+F24+F36+F44+F48+F52+F57+F61+F66+F70) -> 6163 | G71: =SUM(G7+G17+G24+G36+G44+G48+G52+G57+G61+G66+G70) -> 4733 | H71: =SUM(H7+H17+H24+H36+H44+H48+H52+H57+H61+H66+H70) -> 4713 | I71: =SUM(I7+I17+I24+I36+I44+I48+I52+I57+I61+I66+I70) -> 4713 | J71: =SUM(J7+J17+J24+J36+J44++J48+J52+J61+J66+J70) -> 4783 | K71: =SUM(K7+K17+K24+K36+K44++K48+K52+K61+K66+K70) -> 12426 | L71: =SUM(L7+L17+L24+L36+L44++L48+L52+L61+L66+L70) -> 4651 | M71: =SUM(M7+M17+M24+M36+M44++M48+M52+M61+M66+M70) -> 4651 | O71: =SUM(B71:M71) -> 65675
A72: INCOME STREAM
A73: SALARY | B73: 5000 | C73: 5000 | D73: 5000 | E73: 5000 | F73: 6900 | G73: 5000 | H73: 5000 | I73: 5000 | J73: 5000 | K73: 14500 | L73: 5200 | M73: 5200 | O73: =SUM(B73:M73) -> 71800
A74: PRODUCTION | O74: =SUM(B74:M74) -> 0
A75: MY EVENTS | O75: =SUM(B75:M75) -> 0
A76: GIGS | B76: 800 | O76: =SUM(B76:M76) -> 800
A77: TOTAL INCOME | B77: =SUM(B73:B76) -> 5800 | C77: =SUM(C73:C76) -> 5000 | D77: =SUM(D73:D76) -> 5000 | E77: =SUM(E73:E76) -> 5000 | F77: =SUM(F73:F76) -> 6900 | G77: =SUM(G73:G76) -> 5000 | H77: =SUM(H73:H76) -> 5000 | I77: =SUM(I73:I76) -> 5000 | ... M77: =SUM(M73:M76) -> 5200 | O77: =SUM(B77:M77) -> 72600
A78: REMAINING
A80: EXTRA SAVING | B80: =(B77-B71-'[1]House DECO & REPAIR 25'!$C$32) -> 1087 | C80: =(C77-C71-'[1]House DECO & REPAIR 25'!$D$32) -> 287 | D80: =(D77-D71-'[1]House DECO & REPAIR 25'!$E$32) -> 317 | E80: =(E77-E71-'[1]House DECO & REPAIR 25'!$F$32) -> 267 | F80: =(F77-F71-'[1]House DECO & REPAIR 25'!$G$32) -> 737 | G80: =(G77-G71) -> 267 | H80: =(H77-H71) -> 287 | I80: =(I77-I71) -> 287 | J80: =(J77-J71) -> 217 | K80: =(K77-K71) -> 2074 | L80: =(L77-L71) -> 549 | M80: =(M77-M71) -> 549 | O80: =SUM(B80:M80) -> 6925
L81: YEAR END | O81: =SUM(O4:O80) -> 349390
L83: TOTAL UNTOUCHED | O83: =SUM(O66+O70) -> 22500
L84: SAVINGS | O84: =SUM(B80:M80) -> 6925

Sheet PERSONAL BUDGET 2028-2029
A1: 2028 - 2029 | B1: AUGUST | C1: SEPTEMBER | D1: OCTOBER | E1: NOVEMBER | F1: DECEMBER | G1: JANUARY | H1: FEBURARY | I1: MARCH | J1: APRIL | K1: MAY | L1: JUNE | M1: JULY | O1: YEAR TOTAL
A3: HOUSING COSTS
A4: RENT | B4: 1110 | C4: 1110 | D4: 1110 | E4: 1110 | F4: 1110 | G4: 1110 | H4: 1110 | I4: 1110 | J4: 1110 | K4: 1110 | L4: 1175 | M4: 1175 | O4: =SUM(B4:M4) -> 13450
A5: MORTGAGE | B5: 825 | C5: 825 | D5: 825 | E5: 825 | F5: 825 | G5: 825 | H5: 825 | I5: 825 | J5: 825 | K5: 825 | L5: 825 | M5: 825 | O5: =SUM(B5:M5) -> 9900
A6: COUNCIL TAX | B6: 170 | C6: 170 | D6: 170 | E6: 170 | F6: 170 | G6: 170 | H6: 170 | I6: 170 | J6: 170 | K6: 170 | L6: 170 | M6: 170 | O6: =SUM(B6:M6) -> 2040
A7: SUB TOTAL | B7: =SUM(B4:B6) -> 2105 | C7: =SUM(C4:C6) -> 2105 | D7: =SUM(D4:D6) -> 2105 | E7: =SUM(E4:E6) -> 2105 | F7: =SUM(F4:F6) -> 2105 | G7: =SUM(G4:G6) -> 2105 | H7: =SUM(H4:H6) -> 2105 | I7: =SUM(I4:I6) -> 2105 | ... M7: =SUM(M4:M6) -> 2170 | O7: =SUM(O4:O6) -> 25390
A8: UTILITIES
A9: EE | B9: 55 | C9: 55 | D9: 55 | E9: 55 | F9: 55 | G9: 55 | H9: 35 | I9: 35 | J9: 35 | K9: 35 | L9: 35 | M9: 35 | O9: =SUM(B9:M9) -> 540
A10: SKY | B10: 135 | C10: 135 | D10: 135 | E10: 135 | F10: 135 | G10: 135 | H10: 135 | I10: 135 | J10: 135 | K10: 160 | L10: 160 | M10: 160 | O10: =SUM(B10:M10) -> 1695
A11: ECLECTRICITY | B11: 70 | C11: 70 | D11: 70 | E11: 70 | F11: 70 | G11: 70 | H11: 70 | I11: 70 | J11: 70 | K11: 70 | L11: 70 | M11: 70 | O11: =SUM(B11:M11) -> 840
A12: THAMES WATER | B12: 40 | C12: 40 | D12: 40 | E12: 40 | F12: 40 | G12: 40 | H12: 40 | I12: 40 | J12: 40 | K12: 40 | L12: 40 | M12: 40 | O12: =SUM(B12:M12) -> 480
A13: ZURICH | B13: 15 | C13: 15 | D13: 15 | E13: 15 | F13: 15 | G13: 15 | H13: 15 | I13: 15 | J13: 15 | K13: 15 | L13: 15 | M13: 15 | O13: =SUM(B13:M13) -> 180
A14: GAS | B14: 30 | C14: 30 | D14: 30 | E14: 30 | F14: 30 | G14: 30 | H14: 30 | I14: 30 | J14: 30 | K14: 30 | L14: 30 | M14: 30 | O14: =SUM(B14:M14) -> 360
A15: APPLICANE INSURANCE | B15: 25 | C15: 25 | D15: 25 | E15: 25 | F15: 25 | G15: 25 | H15: 25 | I15: 25 | J15: 25 | K15: 25 | L15: 25 | M15: 25 | O15: =SUM(B15:M15) -> 300
A16: LIFE INSURANCE | B16: 15 | C16: 15 | D16: 15 | E16: 15 | F16: 15 | G16: 15 | H16: 15 | I16: 15 | J16: 15 | K16: 15 | L16: 15 | M16: 15 | O16: =SUM(B16:M16) -> 180
A17: SUB TOTAL | B17: =SUM(B9:B16) -> 385 | C17: =SUM(C9:C16) -> 385 | D17: =SUM(D9:D16) -> 385 | E17: =SUM(E9:E16) -> 385 | F17: =SUM(F9:F16) -> 385 | G17: =SUM(G9:G16) -> 385 | H17: =SUM(H9:H16) -> 365 | I17: =SUM(I9:I16) -> 365 | ... M17: =SUM(M9:M16) -> 390 | O17: =SUM(O9:O16) -> 4575
A18: ALLOWANCES
A19: WORK TRAVEL | B19: 60 | C19: 60 | D19: 60 | E19: 60 | F19: 60 | G19: 60 | H19: 60 | I19: 60 | J19: 60 | K19: 60 | L19: 60 | M19: 60 | O19: =SUM(B19:M19) -> 720
A20: UBER | B20: 20 | C20: 20 | D20: 20 | E20: 20 | F20: 20 | G20: 20 | H20: 20 | I20: 20 | J20: 20 | K20: 20 | L20: 20 | M20: 20 | O20: 20
A21: FOOD | B21: 200 | C21: 200 | D21: 200 | E21: 200 | F21: 200 | G21: 200 | H21: 200 | I21: 200 | J21: 200 | K21: 300 | L21: 300 | M21: 300 | O21: =SUM(B21:M21) -> 2700
A22: LUNCH | B22: 70 | C22: 70 | D22: 70 | E22: 70 | F22: 70 | G22: 70 | H22: 70 | I22: 70 | J22: 70 | K22: 70 | L22: 70 | M22: 70 | O22: =SUM(B22:M22) -> 840
A23: MONTHLY ALLOWANCE | B23: 250 | C23: 150 | D23: 100 | E23: 150 | F23: 280 | G23: 150 | H23: 150 | I23: 150 | J23: 280 | K23: 100 | L23: 100 | M23: 100 | O23: =SUM(B23:M23) -> 1960
A24: SUB TOTAL | B24: =SUM(B19:B23) -> 600 | C24: =SUM(C19:C23) -> 500 | D24: =SUM(D19:D23) -> 450 | E24: =SUM(E19:E23) -> 500 | F24: =SUM(F19:F23) -> 630 | G24: =SUM(G19:G23) -> 500 | H24: =SUM(H19:H23) -> 500 | I24: =SUM(I19:I23) -> 500 | ... M24: =SUM(M19:M23) -> 550 | O24: =SUM(O19:O23) -> 6240
A25: SUBSCRIPTIONS
A26: GYM | O26: =SUM(B26:M26) -> 0
A27: SERATO | B27: 10 | C27: 10 | D27: 10 | E27: 10 | F27: 10 | G27: 10 | H27: 10 | I27: 10 | J27: 10 | K27: 10 | L27: 10 | M27: 10 | O27: =SUM(B27:M27) -> 120
A28: SPLICE | B28: 10 | C28: 10 | D28: 10 | E28: 10 | F28: 10 | G28: 10 | H28: 10 | I28: 10 | J28: 10 | K28: 10 | L28: 10 | M28: 10 | O28: =SUM(B28:M28) -> 120
A29: SITE GROUND | B29: 50 | C29: 50 | D29: 50 | E29: 50 | F29: 50 | G29: 50 | H29: 50 | I29: 50 | J29: 50 | K29: 50 | L29: 50 | M29: 50 | O29: =SUM(B29:M29) -> 600
A30: DISNEY PLUS | B30: 5 | C30: 5 | D30: 5 | E30: 5 | F30: 5 | G30: 5 | H30: 5 | I30: 5 | J30: 5 | K30: 5 | L30: 5 | M30: 5 | O30: =SUM(B30:M30) -> 60
A31: NETFLIX | B31: 15 | C31: 15 | D31: 15 | E31: 15 | F31: 15 | G31: 15 | H31: 15 | I31: 15 | J31: 15 | K31: 15 | L31: 15 | M31: 15 | O31: =SUM(B31:M31) -> 180
A32: SPOTIFY | B32: 20 | C32: 20 | D32: 20 | E32: 20 | F32: 20 | G32: 20 | H32: 20 | I32: 20 | J32: 20 | K32: 20 | L32: 20 | M32: 20 | O32: =SUM(B32:M32) -> 240
A33: MICROSOFT | B33: 8 | C33: 8 | D33: 8 | E33: 8 | F33: 8 | G33: 8 | H33: 8 | I33: 8 | J33: 8 | K33: 6 | L33: 6 | M33: 6 | O33: =SUM(B33:M33) -> 90
A34: APPLE ITUNES | B34: 12 | C34: 12 | D34: 12 | E34: 12 | F34: 12 | G34: 12 | H34: 12 | I34: 12 | J34: 12 | K34: 12 | L34: 12 | M34: 12 | O34: =SUM(B34:M34) -> 144
A35: REVOLUT | B35: 8 | C35: 8 | D35: 8 | E35: 8 | F35: 8 | G35: 8 | H35: 8 | I35: 8 | J35: 8 | K35: 8 | L35: 8 | M35: 8 | O35: =SUM(B35:M35) -> 96
A36: SUB TOTAL | B36: =SUM(B26:B35) -> 138 | C36: =SUM(C26:C35) -> 138 | D36: =SUM(D26:D35) -> 138 | E36: =SUM(E26:E35) -> 138 | F36: =SUM(F26:F35) -> 138 | G36: =SUM(G26:G35) -> 138 | H36: =SUM(H26:H35) -> 138 | I36: =SUM(I26:I35) -> 138 | ... M36: =SUM(M26:M35) -> 136 | O36: =SUM(O26:O35) -> 1650
A37: CHILDCARE
A38: JAYDA | O38: =SUM(B38:M38) -> 0
A39: JAYDA ALLOWANCE | B39: 180 | C39: 180 | D39: 180 | E39: 180 | F39: 180 | G39: 180 | H39: 180 | I39: 180 | J39: 180 | K39: 180 | L39: 180 | M39: 180 | O39: =SUM(B39:M39) -> 2160
A40: JAYDA SAVING 2 | B40: 50 | C40: 50 | D40: 50 | E40: 50 | F40: 50 | G40: 50 | H40: 50 | I40: 50 | J40: 50 | K40: 50 | L40: 50 | M40: 50 | O40: =SUM(B40:M40) -> 600
A41: JAYDA DANCE | O41: =SUM(B41:M41) -> 0
A42: JAYDA HOLIDAY | O42: =SUM(B42:M42) -> 0
A43: JAYDA SCHOOL | O43: =SUM(B43:M43) -> 0
A44: SUB TOTAL | B44: =SUM(B38:B43) -> 230 | C44: =SUM(C38:C43) -> 230 | D44: =SUM(D38:D43) -> 230 | E44: =SUM(E38:E43) -> 230 | F44: =SUM(F38:F43) -> 230 | G44: =SUM(G38:G43) -> 230 | H44: =SUM(H38:H43) -> 230 | I44: =SUM(I38:I43) -> 230 | ... M44: =SUM(M38:M43) -> 230 | O44: =SUM(O38:O43) -> 2760
A45: SELF DEVELOPMEMT
A46: COURSE | O46: =SUM(B46:M46) -> 0
A48: SUB TOTAL | B48: =SUM(B46) -> 0 | C48: =SUM(C46) -> 0 | D48: =SUM(D46) -> 0 | E48: =SUM(E46) -> 0 | F48: =SUM(F46) -> 0 | G48: =SUM(G46) -> 0 | H48: =SUM(H46) -> 0 | I48: =SUM(I46) -> 0 | ... M48: =SUM(M46) -> 0 | O48: =SUM(O46:O47) -> 0
A49: LOAN DEBTS
A50: CARD | O50: =SUM(B50:M50) -> 0
A51: AUDIO GEAR | B51: 175 | C51: 175 | D51: 175 | E51: 175 | F51: 175 | G51: 175 | H51: 175 | I51: 175 | J51: 175 | K51: 175 | L51: 175 | M51: 175 | O51: =SUM(B51:M51) -> 2100
A52: SUB TOTAL | B52: =SUM(B50:B51) -> 175 | C52: =SUM(C50:C51) -> 175 | D52: =SUM(D50:D51) -> 175 | E52: =SUM(E50:E51) -> 175 | F52: =SUM(F50:F51) -> 175 | G52: =SUM(G50:G51) -> 175 | H52: =SUM(H50:H51) -> 175 | I52: =SUM(I50:I51) -> 175 | ... M52: =SUM(M50:M51) -> 175 | O52: =SUM(B52:M52) -> 2100
A53: SELF CARE
A54: BARBERS | B54: 40 | C54: 40 | D54: 60 | E54: 60 | F54: 60 | G54: 60 | H54: 60 | I54: 60 | J54: 60 | K54: 60 | L54: 60 | M54: 60 | O54: =SUM(B54:M54) -> 680
A55: BODY CARE | K55: 100 | O55: =SUM(B55:M55) -> 100
A56: CLOTHES | O56: =SUM(B56:M56) -> 0
A57: SUB TOTAL | B57: =SUM(B54:B56) -> 40 | C57: =SUM(C54:C56) -> 40 | D57: =SUM(D54:D56) -> 60 | E57: =SUM(E54:E56) -> 60 | F57: =SUM(F54:F56) -> 60 | G57: =SUM(G54:G56) -> 60 | H57: =SUM(H54:H56) -> 60 | I57: =SUM(I54:I56) -> 60 | ... M57: =SUM(M54:M56) -> 60 | O57: =SUM(O54:O56) -> 780
A58: OTHER EXPENSIVE
A59: OTHER | O59: =SUM(B59:M59) -> 0
A60: GIFTS | O60: =SUM(B60:M60) -> 0
A61: SUB TOTAL | B61: =SUM(B58:B60) -> 0 | C61: =SUM(C58:C60) -> 0 | D61: =SUM(D58:D60) -> 0 | E61: =SUM(E58:E60) -> 0 | F61: =SUM(F58:F60) -> 0 | G61: =SUM(G58:G60) -> 0 | H61: =SUM(H58:H60) -> 0 | I61: =SUM(I58:I60) -> 0 | ... M61: =SUM(M58:M60) -> 0 | O61: =SUM(O58:O60) -> 0
A62: SAVINGS
A63: EMERGENCY FUNDS | B63: 300 | C63: 300 | D63: 300 | E63: 300 | F63: 300 | G63: 300 | H63: 300 | I63: 300 | J63: 300 | L63: 600 | M63: 600 | O63: =SUM(B63:M63) -> 3900
A64: SINGLE SAVING | C64: 100 | D64: 100 | E64: 100 | F64: 100 | G64: 100 | H64: 100 | I64: 100 | J64: 100 | K64: 1000 | L64: 100 | M64: 100 | O64: =SUM(B64:M64) -> 2000
A65: HOME DEPOSIT | B65: 700 | C65: 700 | D65: 700 | E65: 700 | F65: 700 | G65: 700 | H65: 700 | I65: 700 | J65: 700 | K65: 9000 | L65: 300 | M65: 300 | O65: =SUM(B65:M65) -> 15900
A66: SUB TOTAL | B66: =SUM(B63:B65) -> 1000 | C66: =SUM(C63:C65) -> 1100 | D66: =SUM(D63:D65) -> 1100 | E66: =SUM(E63:E65) -> 1100 | F66: =SUM(F63:F65) -> 1100 | G66: =SUM(G63:G65) -> 1100 | H66: =SUM(H63:H65) -> 1100 | I66: =SUM(I63:I65) -> 1100 | ... M66: =SUM(M63:M65) -> 1000 | O66: =SUM(O63:O65) -> 21800
A67: INVESTMENT CONTRIBUTION
A69: TRADING 212 | B69: 50 | C69: 50 | D69: 50 | E69: 50 | F69: 50 | G69: 50 | H69: 50 | I69: 50 | J69: 50 | K69: 50 | L69: 50 | M69: 50 | O69: =SUM(B69:M69) -> 600
A70: SUB TOTAL | B70: =SUM(B68:B69) -> 50 | C70: =SUM(C68:C69) -> 50 | D70: =SUM(D68:D69) -> 50 | E70: =SUM(E68:E69) -> 50 | F70: =SUM(F68:F69) -> 50 | G70: =SUM(G68:G69) -> 50 | H70: =SUM(H68:H69) -> 50 | I70: =SUM(I68:I69) -> 50 | ... M70: =SUM(M68:M69) -> 50 | O70: =SUM(O68:O69) -> 600
A71: GRAND TOTAL | B71: =SUM(B7+B17+B24+B36+B44+B48+B52+B57+B61+B66+B70) -> 4723 | C71: =SUM(C7+C17+C24+C36+C44+C48+C52+C57+C61+C66+C70) -> 4723 | D71: =SUM(D7+D17+D24+D36+D44+D48+D52+D57+D61+D66+D70) -> 4693 | E71: =SUM(E7+E17+E24+E36+E44+E48+E52+E57+E61+E66+E70) -> 4743 | F71: =SUM(F7+F17+F24+F36+F44+F48+F52+F57+F61+F66+F70) -> 4873 | G71: =SUM(G7+G17+G24+G36+G44+G48+G52+G57+G61+G66+G70) -> 4743 | H71: =SUM(H7+H17+H24+H36+H44+H48+H52+H57+H61+H66+H70) -> 4723 | I71: =SUM(I7+I17+I24+I36+I44+I48+I52+I57+I61+I66+I70) -> 4723 | J71: =SUM(J7+J17+J24+J36+J44++J48+J52+J61+J66+J70) -> 4793 | K71: =SUM(K7+K17+K24+K36+K44++K48+K52+K61+K66+K70) -> 13636 | L71: =SUM(L7+L17+L24+L36+L44++L48+L52+L61+L66+L70) -> 4701 | M71: =SUM(M7+M17+M24+M36+M44++M48+M52+M61+M66+M70) -> 4701 | O71: =SUM(B71:M71) -> 65775
A72: INCOME STREAM
A73: SALARY | B73: 5200 | C73: 5200 | D73: 5200 | E73: 5200 | F73: 5200 | G73: 5200 | H73: 5200 | I73: 5200 | J73: 5200 | K73: 14500 | L73: 5400 | M73: 5400 | O73: =SUM(B73:M73) -> 72100
A74: PRODUCTION | O74: =SUM(B74:M74) -> 0
A75: MY EVENTS | O75: =SUM(B75:M75) -> 0
A76: GIGS | B76: 800 | O76: =SUM(B76:M76) -> 800
A77: TOTAL INCOME | B77: =SUM(B73:B76) -> 6000 | C77: =SUM(C73:C76) -> 5200 | D77: =SUM(D73:D76) -> 5200 | E77: =SUM(E73:E76) -> 5200 | F77: =SUM(F73:F76) -> 5200 | G77: =SUM(G73:G76) -> 5200 | H77: =SUM(H73:H76) -> 5200 | I77: =SUM(I73:I76) -> 5200 | ... M77: =SUM(M73:M76) -> 5400 | O77: =SUM(B77:M77) -> 72900
A78: REMAINING
A80: EXTRA SAVING | B80: =(B77-B71-'[1]House DECO & REPAIR 25'!$C$32) -> 1277 | C80: =(C77-C71-'[1]House DECO & REPAIR 25'!$D$32) -> 477 | D80: =(D77-D71-'[1]House DECO & REPAIR 25'!$E$32) -> 507 | E80: =(E77-E71-'[1]House DECO & REPAIR 25'!$F$32) -> 457 | F80: =(F77-F71-'[1]House DECO & REPAIR 25'!$G$32) -> 327 | G80: =(G77-G71) -> 457 | H80: =(H77-H71) -> 477 | I80: =(I77-I71) -> 477 | J80: =(J77-J71) -> 407 | K80: =(K77-K71) -> 864 | L80: =(L77-L71) -> 699 | M80: =(M77-M71) -> 699 | O80: =SUM(B80:M80) -> 7125
L81: YEAR END | O81: =SUM(O4:O80) -> 350490
L83: TOTAL UNTOUCHED | O83: =SUM(O66+O70) -> 22400
L84: SAVINGS | O84: =SUM(B80:M80) -> 7125

Sheet PERSONAL BUDGET 2029-2030
A1: 2029 - 2030 | B1: AUGUST | C1: SEPTEMBER | D1: OCTOBER | E1: NOVEMBER | F1: DECEMBER | G1: JANUARY | H1: FEBURARY | I1: MARCH | J1: APRIL | K1: MAY | L1: JUNE | M1: JULY | O1: YEAR TOTAL
A3: HOUSING COSTS
A4: RENT | B4: 1110 | C4: 1110 | D4: 1110 | E4: 1110 | F4: 1110 | G4: 1110 | H4: 1110 | I4: 1110 | J4: 1110 | K4: 1110 | L4: 1175 | M4: 1175 | O4: =SUM(B4:M4) -> 13450
A5: MORTGAGE | B5: 825 | C5: 825 | D5: 825 | E5: 825 | F5: 825 | G5: 825 | H5: 825 | I5: 825 | J5: 825 | K5: 825 | L5: 825 | M5: 825 | O5: =SUM(B5:M5) -> 9900
A6: COUNCIL TAX | B6: 170 | C6: 170 | D6: 170 | E6: 170 | F6: 170 | G6: 170 | H6: 170 | I6: 170 | J6: 170 | K6: 170 | L6: 170 | M6: 170 | O6: =SUM(B6:M6) -> 2040
A7: SUB TOTAL | B7: =SUM(B4:B6) -> 2105 | C7: =SUM(C4:C6) -> 2105 | D7: =SUM(D4:D6) -> 2105 | E7: =SUM(E4:E6) -> 2105 | F7: =SUM(F4:F6) -> 2105 | G7: =SUM(G4:G6) -> 2105 | H7: =SUM(H4:H6) -> 2105 | I7: =SUM(I4:I6) -> 2105 | ... M7: =SUM(M4:M6) -> 2170 | O7: =SUM(O4:O6) -> 25390
A8: UTILITIES
A9: EE | B9: 55 | C9: 55 | D9: 55 | E9: 55 | F9: 55 | G9: 55 | H9: 35 | I9: 35 | J9: 35 | K9: 35 | L9: 35 | M9: 35 | O9: =SUM(B9:M9) -> 540
A10: SKY | B10: 135 | C10: 135 | D10: 135 | E10: 135 | F10: 135 | G10: 135 | H10: 135 | I10: 135 | J10: 135 | K10: 160 | L10: 160 | M10: 160 | O10: =SUM(B10:M10) -> 1695
A11: ECLECTRICITY | B11: 70 | C11: 70 | D11: 70 | E11: 70 | F11: 70 | G11: 70 | H11: 70 | I11: 70 | J11: 70 | K11: 70 | L11: 70 | M11: 70 | O11: =SUM(B11:M11) -> 840
A12: THAMES WATER | B12: 40 | C12: 40 | D12: 40 | E12: 40 | F12: 40 | G12: 40 | H12: 40 | I12: 40 | J12: 40 | K12: 40 | L12: 40 | M12: 40 | O12: =SUM(B12:M12) -> 480
A13: ZURICH | B13: 15 | C13: 15 | D13: 15 | E13: 15 | F13: 15 | G13: 15 | H13: 15 | I13: 15 | J13: 15 | K13: 15 | L13: 15 | M13: 15 | O13: =SUM(B13:M13) -> 180
A14: GAS | B14: 30 | C14: 30 | D14: 30 | E14: 30 | F14: 30 | G14: 30 | H14: 30 | I14: 30 | J14: 30 | K14: 30 | L14: 30 | M14: 30 | O14: =SUM(B14:M14) -> 360
A15: APPLICANE INSURANCE | B15: 25 | C15: 25 | D15: 25 | E15: 25 | F15: 25 | G15: 25 | H15: 25 | I15: 25 | J15: 25 | K15: 25 | L15: 25 | M15: 25 | O15: =SUM(B15:M15) -> 300
A16: LIFE INSURANCE | B16: 15 | C16: 15 | D16: 15 | E16: 15 | F16: 15 | G16: 15 | H16: 15 | I16: 15 | J16: 15 | K16: 15 | L16: 15 | M16: 15 | O16: =SUM(B16:M16) -> 180
A17: SUB TOTAL | B17: =SUM(B9:B16) -> 385 | C17: =SUM(C9:C16) -> 385 | D17: =SUM(D9:D16) -> 385 | E17: =SUM(E9:E16) -> 385 | F17: =SUM(F9:F16) -> 385 | G17: =SUM(G9:G16) -> 385 | H17: =SUM(H9:H16) -> 365 | I17: =SUM(I9:I16) -> 365 | ... M17: =SUM(M9:M16) -> 390 | O17: =SUM(O9:O16) -> 4575
A18: ALLOWANCES
A19: WORK TRAVEL | B19: 60 | C19: 60 | D19: 60 | E19: 60 | F19: 60 | G19: 60 | H19: 60 | I19: 60 | J19: 60 | K19: 60 | L19: 60 | M19: 60 | O19: =SUM(B19:M19) -> 720
A20: UBER | B20: 20 | C20: 20 | D20: 20 | E20: 20 | F20: 20 | G20: 20 | H20: 20 | I20: 20 | J20: 20 | K20: 20 | L20: 20 | M20: 20 | O20: 20
A21: FOOD | B21: 200 | C21: 200 | D21: 200 | E21: 200 | F21: 200 | G21: 200 | H21: 200 | I21: 200 | J21: 200 | K21: 300 | L21: 300 | M21: 300 | O21: =SUM(B21:M21) -> 2700
A22: LUNCH | B22: 70 | C22: 70 | D22: 70 | E22: 70 | F22: 70 | G22: 70 | H22: 70 | I22: 70 | J22: 70 | K22: 70 | L22: 70 | M22: 70 | O22: =SUM(B22:M22) -> 840
A23: MONTHLY ALLOWANCE | B23: 250 | C23: 150 | D23: 100 | E23: 150 | F23: 280 | G23: 150 | H23: 150 | I23: 150 | J23: 280 | K23: 100 | L23: 100 | M23: 100 | O23: =SUM(B23:M23) -> 1960
A24: SUB TOTAL | B24: =SUM(B19:B23) -> 600 | C24: =SUM(C19:C23) -> 500 | D24: =SUM(D19:D23) -> 450 | E24: =SUM(E19:E23) -> 500 | F24: =SUM(F19:F23) -> 630 | G24: =SUM(G19:G23) -> 500 | H24: =SUM(H19:H23) -> 500 | I24: =SUM(I19:I23) -> 500 | ... M24: =SUM(M19:M23) -> 550 | O24: =SUM(O19:O23) -> 6240
A25: SUBSCRIPTIONS
A26: GYM | O26: =SUM(B26:M26) -> 0
A27: SERATO | B27: 10 | C27: 10 | D27: 10 | E27: 10 | F27: 10 | G27: 10 | H27: 10 | I27: 10 | J27: 10 | K27: 10 | L27: 10 | M27: 10 | O27: =SUM(B27:M27) -> 120
A28: SPLICE | B28: 10 | C28: 10 | D28: 10 | E28: 10 | F28: 10 | G28: 10 | H28: 10 | I28: 10 | J28: 10 | K28: 10 | L28: 10 | M28: 10 | O28: =SUM(B28:M28) -> 120
A29: SITE GROUND | B29: 50 | C29: 50 | D29: 50 | E29: 50 | F29: 50 | G29: 50 | H29: 50 | I29: 50 | J29: 50 | K29: 50 | L29: 50 | M29: 50 | O29: =SUM(B29:M29) -> 600
A30: DISNEY PLUS | B30: 8 | C30: 8 | D30: 8 | E30: 8 | F30: 8 | G30: 8 | H30: 8 | I30: 8 | J30: 8 | K30: 8 | L30: 8 | M30: 8 | O30: =SUM(B30:M30) -> 96
A31: NETFLIX | B31: 15 | C31: 15 | D31: 15 | E31: 15 | F31: 15 | G31: 15 | H31: 15 | I31: 15 | J31: 15 | K31: 15 | L31: 15 | M31: 15 | O31: =SUM(B31:M31) -> 180
A32: SPOTIFY | B32: 20 | C32: 20 | D32: 20 | E32: 20 | F32: 20 | G32: 20 | H32: 20 | I32: 20 | J32: 20 | K32: 20 | L32: 20 | M32: 20 | O32: =SUM(B32:M32) -> 240
A33: MICROSOFT | B33: 8 | C33: 8 | D33: 8 | E33: 8 | F33: 8 | G33: 8 | H33: 8 | I33: 8 | J33: 8 | K33: 6 | L33: 6 | M33: 6 | O33: =SUM(B33:M33) -> 90
A34: APPLE ITUNES | B34: 12 | C34: 12 | D34: 12 | E34: 12 | F34: 12 | G34: 12 | H34: 12 | I34: 12 | J34: 12 | K34: 12 | L34: 12 | M34: 12 | O34: =SUM(B34:M34) -> 144
A35: REVOLUT | B35: 8 | C35: 8 | D35: 8 | E35: 8 | F35: 8 | G35: 8 | H35: 8 | I35: 8 | J35: 8 | K35: 8 | L35: 8 | M35: 8 | O35: =SUM(B35:M35) -> 96
A36: SUB TOTAL | B36: =SUM(B26:B35) -> 141 | C36: =SUM(C26:C35) -> 141 | D36: =SUM(D26:D35) -> 141 | E36: =SUM(E26:E35) -> 141 | F36: =SUM(F26:F35) -> 141 | G36: =SUM(G26:G35) -> 141 | H36: =SUM(H26:H35) -> 141 | I36: =SUM(I26:I35) -> 141 | ... M36: =SUM(M26:M35) -> 139 | O36: =SUM(O26:O35) -> 1686
A37: CHILDCARE
A38: JAYDA | O38: =SUM(B38:M38) -> 0
A39: JAYDA ALLOWANCE | B39: 180 | C39: 180 | D39: 180 | E39: 180 | F39: 180 | G39: 180 | H39: 180 | I39: 180 | J39: 180 | K39: 180 | L39: 180 | M39: 180 | O39: =SUM(B39:M39) -> 2160
A40: JAYDA SAVING 2 | B40: 50 | C40: 50 | D40: 50 | E40: 50 | F40: 50 | G40: 50 | H40: 50 | I40: 50 | J40: 50 | K40: 50 | L40: 50 | M40: 50 | O40: =SUM(B40:M40) -> 600
A41: JAYDA DANCE | O41: =SUM(B41:M41) -> 0
A42: JAYDA HOLIDAY | O42: =SUM(B42:M42) -> 0
A43: JAYDA SCHOOL | O43: =SUM(B43:M43) -> 0
A44: SUB TOTAL | B44: =SUM(B38:B43) -> 230 | C44: =SUM(C38:C43) -> 230 | D44: =SUM(D38:D43) -> 230 | E44: =SUM(E38:E43) -> 230 | F44: =SUM(F38:F43) -> 230 | G44: =SUM(G38:G43) -> 230 | H44: =SUM(H38:H43) -> 230 | I44: =SUM(I38:I43) -> 230 | ... M44: =SUM(M38:M43) -> 230 | O44: =SUM(O38:O43) -> 2760
A45: SELF DEVELOPMEMT
A46: COURSE | O46: =SUM(B46:M46) -> 0
A48: SUB TOTAL | B48: =SUM(B46) -> 0 | C48: =SUM(C46) -> 0 | D48: =SUM(D46) -> 0 | E48: =SUM(E46) -> 0 | F48: =SUM(F46) -> 0 | G48: =SUM(G46) -> 0 | H48: =SUM(H46) -> 0 | I48: =SUM(I46) -> 0 | ... M48: =SUM(M46) -> 0 | O48: =SUM(O46:O47) -> 0
A49: LOAN DEBTS
A50: CARD | O50: =SUM(B50:M50) -> 0
A51: AUDIO GEAR | B51: 175 | C51: 175 | D51: 175 | E51: 175 | F51: 175 | G51: 175 | H51: 175 | I51: 175 | J51: 175 | K51: 175 | L51: 175 | M51: 175 | O51: =SUM(B51:M51) -> 2100
A52: SUB TOTAL | B52: =SUM(B50:B51) -> 175 | C52: =SUM(C50:C51) -> 175 | D52: =SUM(D50:D51) -> 175 | E52: =SUM(E50:E51) -> 175 | F52: =SUM(F50:F51) -> 175 | G52: =SUM(G50:G51) -> 175 | H52: =SUM(H50:H51) -> 175 | I52: =SUM(I50:I51) -> 175 | ... M52: =SUM(M50:M51) -> 175 | O52: =SUM(B52:M52) -> 2100
A53: SELF CARE
A54: BARBERS | B54: 40 | C54: 40 | D54: 60 | E54: 60 | F54: 60 | G54: 60 | H54: 60 | I54: 60 | J54: 60 | K54: 60 | L54: 60 | M54: 60 | O54: =SUM(B54:M54) -> 680
A55: BODY CARE | K55: 100 | O55: =SUM(B55:M55) -> 100
A56: CLOTHES | O56: =SUM(B56:M56) -> 0
A57: SUB TOTAL | B57: =SUM(B54:B56) -> 40 | C57: =SUM(C54:C56) -> 40 | D57: =SUM(D54:D56) -> 60 | E57: =SUM(E54:E56) -> 60 | F57: =SUM(F54:F56) -> 60 | G57: =SUM(G54:G56) -> 60 | H57: =SUM(H54:H56) -> 60 | I57: =SUM(I54:I56) -> 60 | ... M57: =SUM(M54:M56) -> 60 | O57: =SUM(O54:O56) -> 780
A58: OTHER EXPENSIVE
A59: OTHER | O59: =SUM(B59:M59) -> 0
A60: GIFTS | O60: =SUM(B60:M60) -> 0
A61: SUB TOTAL | B61: =SUM(B58:B60) -> 0 | C61: =SUM(C58:C60) -> 0 | D61: =SUM(D58:D60) -> 0 | E61: =SUM(E58:E60) -> 0 | F61: =SUM(F58:F60) -> 0 | G61: =SUM(G58:G60) -> 0 | H61: =SUM(H58:H60) -> 0 | I61: =SUM(I58:I60) -> 0 | ... M61: =SUM(M58:M60) -> 0 | O61: =SUM(O58:O60) -> 0
A62: SAVINGS
A63: EMERGENCY FUNDS | B63: 300 | C63: 300 | D63: 300 | E63: 300 | F63: 300 | G63: 300 | H63: 300 | I63: 300 | J63: 300 | O63: =SUM(B63:M63) -> 2700
A64: SINGLE SAVING | C64: 100 | D64: 100 | E64: 100 | F64: 100 | G64: 100 | H64: 100 | I64: 100 | J64: 100 | K64: 100 | L64: 100 | M64: 100 | O64: =SUM(B64:M64) -> 1100
A65: HOME DEPOSIT | B65: 700 | C65: 700 | D65: 700 | E65: 700 | F65: 700 | G65: 700 | H65: 700 | I65: 700 | J65: 700 | K65: 9000 | L65: 300 | M65: 300 | O65: =SUM(B65:M65) -> 15900
A66: SUB TOTAL | B66: =SUM(B63:B65) -> 1000 | C66: =SUM(C63:C65) -> 1100 | D66: =SUM(D63:D65) -> 1100 | E66: =SUM(E63:E65) -> 1100 | F66: =SUM(F63:F65) -> 1100 | G66: =SUM(G63:G65) -> 1100 | H66: =SUM(H63:H65) -> 1100 | I66: =SUM(I63:I65) -> 1100 | ... M66: =SUM(M63:M65) -> 400 | O66: =SUM(O63:O65) -> 19700
A67: INVESTMENT CONTRIBUTION
A69: TRADING 212 | B69: 50 | C69: 50 | D69: 50 | E69: 50 | F69: 50 | G69: 50 | H69: 50 | I69: 50 | J69: 50 | K69: 50 | L69: 50 | M69: 50 | O69: =SUM(B69:M69) -> 600
A70: SUB TOTAL | B70: =SUM(B68:B69) -> 50 | C70: =SUM(C68:C69) -> 50 | D70: =SUM(D68:D69) -> 50 | E70: =SUM(E68:E69) -> 50 | F70: =SUM(F68:F69) -> 50 | G70: =SUM(G68:G69) -> 50 | H70: =SUM(H68:H69) -> 50 | I70: =SUM(I68:I69) -> 50 | ... M70: =SUM(M68:M69) -> 50 | O70: =SUM(O68:O69) -> 600
A71: GRAND TOTAL | B71: =SUM(B7+B17+B24+B36+B44+B48+B52+B57+B61+B66+B70) -> 4726 | C71: =SUM(C7+C17+C24+C36+C44+C48+C52+C57+C61+C66+C70) -> 4726 | D71: =SUM(D7+D17+D24+D36+D44+D48+D52+D57+D61+D66+D70) -> 4696 | E71: =SUM(E7+E17+E24+E36+E44+E48+E52+E57+E61+E66+E70) -> 4746 | F71: =SUM(F7+F17+F24+F36+F44+F48+F52+F57+F61+F66+F70) -> 4876 | G71: =SUM(G7+G17+G24+G36+G44+G48+G52+G57+G61+G66+G70) -> 4746 | H71: =SUM(H7+H17+H24+H36+H44+H48+H52+H57+H61+H66+H70) -> 4726 | I71: =SUM(I7+I17+I24+I36+I44+I48+I52+I57+I61+I66+I70) -> 4726 | J71: =SUM(J7+J17+J24+J36+J44++J48+J52+J61+J66+J70) -> 4796 | K71: =SUM(K7+K17+K24+K36+K44++K48+K52+K61+K66+K70) -> 12739 | L71: =SUM(L7+L17+L24+L36+L44++L48+L52+L61+L66+L70) -> 4104 | M71: =SUM(M7+M17+M24+M36+M44++M48+M52+M61+M66+M70) -> 4104 | O71: =SUM(B71:M71) -> 63711
A72: INCOME STREAM
A73: SALARY | B73: 5400 | C73: 5400 | D73: 5400 | E73: 5400 | F73: 5400 | G73: 5400 | H73: 5400 | I73: 5400 | J73: 5400 | K73: 14500 | L73: 5400 | M73: 5400 | O73: =SUM(B73:M73) -> 73900
A74: PRODUCTION | O74: =SUM(B74:M74) -> 0
O75: =SUM(B75:M75) -> 0
A76: GIGS | B76: 800 | O76: =SUM(B76:M76) -> 800
A77: TOTAL INCOME | B77: =SUM(B73:B76) -> 6200 | C77: =SUM(C73:C76) -> 5400 | D77: =SUM(D73:D76) -> 5400 | E77: =SUM(E73:E76) -> 5400 | F77: =SUM(F73:F76) -> 5400 | G77: =SUM(G73:G76) -> 5400 | H77: =SUM(H73:H76) -> 5400 | I77: =SUM(I73:I76) -> 5400 | ... M77: =SUM(M73:M76) -> 5400 | O77: =SUM(B77:M77) -> 74700
A78: REMAINING
A80: EXTRA SAVING | B80: =(B77-B71-'[1]House DECO & REPAIR 25'!$C$32) -> 1474 | C80: =(C77-C71-'[1]House DECO & REPAIR 25'!$D$32) -> 674 | D80: =(D77-D71-'[1]House DECO & REPAIR 25'!$E$32) -> 704 | E80: =(E77-E71-'[1]House DECO & REPAIR 25'!$F$32) -> 654 | F80: =(F77-F71-'[1]House DECO & REPAIR 25'!$G$32) -> 524 | G80: =(G77-G71) -> 654 | H80: =(H77-H71) -> 674 | I80: =(I77-I71) -> 674 | J80: =(J77-J71) -> 604 | K80: =(K77-K71) -> 1761 | L80: =(L77-L71) -> 1296 | M80: =(M77-M71) -> 1296 | O80: =SUM(B80:M80) -> 10989
L81: YEAR END | O81: =SUM(O4:O80) -> 351762
L83: TOTAL UNTOUCHED | O83: =SUM(O66+O70) -> 20300
L84: SAVINGS | O84: =SUM(B80:M80) -> 10989

Sheet YEARLY TOTALS
B2: 2025/2026 | C2: 2026/2027 | D2: 2027/2028 | E2: 2028/2029 | F2: 2029/2030
A4: HOME DEPOSIT | B4: =SUM('PERSONAL BUDGET 2025-2026'!U71) -> 1000 | C4: =SUM('PERSONAL BUDGET 2026-2027'!O65) -> 7200 | D4: =SUM('PERSONAL BUDGET 2027-2028'!O65) -> 8500 | E4: =SUM('PERSONAL BUDGET 2028-2029'!O65) -> 15900 | F4: =SUM('PERSONAL BUDGET 2029-2030'!O65) -> 15900 | G4: =SUM(B4:F4) -> 48500
A5: EMERGENCY | B5: =SUM('PERSONAL BUDGET 2025-2026'!U69) -> 4300 | C5: =SUM('PERSONAL BUDGET 2026-2027'!O63) -> 11900 | D5: =SUM('PERSONAL BUDGET 2027-2028'!O63) -> 11900 | E5: =SUM('PERSONAL BUDGET 2028-2029'!O63) -> 3900 | F5: =SUM('PERSONAL BUDGET 2029-2030'!O63) -> 2700 | G5: =SUM(B5:F5) -> 34700
A6: SAVING | B6: =SUM('PERSONAL BUDGET 2025-2026'!U70) -> 0 | C6: =SUM('PERSONAL BUDGET 2026-2027'!O64) -> 1500 | D6: =SUM('PERSONAL BUDGET 2027-2028'!O64) -> 1500 | E6: =SUM('PERSONAL BUDGET 2028-2029'!O64) -> 2000 | F6: =SUM('PERSONAL BUDGET 2029-2030'!O64) -> 1100 | G6: =SUM(B6:F6) -> 6100
A7: INVESTMENT | B7: =SUM('PERSONAL BUDGET 2025-2026'!U76) -> 150 | C7: =SUM('PERSONAL BUDGET 2026-2027'!O70) -> 600 | D7: =SUM('PERSONAL BUDGET 2027-2028'!O70) -> 600 | E7: =SUM('PERSONAL BUDGET 2028-2029'!O70) -> 600 | F7: =SUM('PERSONAL BUDGET 2029-2030'!O70) -> 600 | G7: =SUM(B7:F7) -> 2550
A10: UNTOUCHED FUNDS | B10: =SUM(B4:B7) -> 5450 | C10: =SUM(C4:C7) -> 21200 | D10: =SUM(D4:D7) -> 22500 | E10: =SUM(E4:E7) -> 22400 | F10: =SUM(F4:F7) -> 20300 | G10: =SUM(B10:F10) -> 91850
A11: INVESTMENT RETURNS | B11: 0 | C11: 0 | D11: 0 | E11: 0 | F11: 0 | G11: =SUM(B11:E11) -> 0
A12: YEAR LEFT OVER | B12: =SUM('PERSONAL BUDGET 2025-2026'!U90) -> 1810 | C12: =SUM('PERSONAL BUDGET 2026-2027'!O80) -> 4855 | D12: =SUM('PERSONAL BUDGET 2027-2028'!O80) -> 6925 | E12: =SUM('PERSONAL BUDGET 2028-2029'!O80) -> 7125 | F12: =SUM('PERSONAL BUDGET 2029-2030'!O80) -> 10989 | G12: =SUM(B12:F12) -> 31704
F13: TOTAL ASSETS | G13: {=SUM(G10:G12-C21-C22-C23-C24)} -> 123554
A18: DEDUCTIONS
B19: WITHDRAWAL | C19: AMOUNT | D19: DATE
B21: HOME DEPOSIT | C21: 0
B22: HOLIDAY | C22: 0
B23: CAR | C23: 0
B24: WEDDING | C24: 0
